{"version":3,"kind":"Notebook","sha256":"9f682675d70475411adc11aa06815075dc986a33f085f9aaeddb58bbfd4178fe","slug":"economics.financial-economics.investment-strategies.momentum","location":"/economics/financial_economics/investment_strategies/momentum.ipynb","dependencies":[],"frontmatter":{"title":"モメンタム","content_includes_title":false,"kernelspec":{"name":"python3","display_name":"Python 3 (ipykernel)","language":"python"},"authors":[{"nameParsed":{"literal":"mitama","family":"mitama"},"name":"mitama","id":"contributors-myst-generated-uid-0"}],"github":"https://github.com/nigimitama/notes","copyright":"© mitama","numbering":{"title":{"offset":3}},"source_url":"https://github.com/nigimitama/notes/blob/main/book/economics/financial_economics/investment_strategies/momentum.ipynb","edit_url":"https://github.com/nigimitama/notes/edit/main/book/economics/financial_economics/investment_strategies/momentum.ipynb","exports":[{"format":"ipynb","filename":"momentum.ipynb","url":"/notes/build/momentum-cee6dbf7097655d8f63966402d572e62.ipynb"}]},"widgets":{},"mdast":{"type":"root","children":[{"type":"block","kind":"notebook-content","children":[{"type":"heading","depth":3,"position":{"start":{"line":1,"column":1},"end":{"line":1,"column":1}},"children":[{"type":"text","value":"定義","position":{"start":{"line":1,"column":1},"end":{"line":1,"column":1}},"key":"q1QfdP0ejR"}],"identifier":"id","label":"定義","html_id":"id","implicit":true,"key":"FM1ebWreBO"},{"type":"paragraph","position":{"start":{"line":3,"column":1},"end":{"line":3,"column":1}},"children":[{"type":"text","value":"モメンタム／リバーサル現象とは、マーケットで観測されるアノマリー（効率的市場仮説では説明が難しい現象）。","position":{"start":{"line":3,"column":1},"end":{"line":3,"column":1}},"key":"j7r8ZLqN4e"}],"key":"uz4Tpa2z4U"},{"type":"paragraph","position":{"start":{"line":5,"column":1},"end":{"line":5,"column":1}},"children":[{"type":"text","value":"モメンタム現象とは、「過去の一定期間に他の銘柄と比べてリターン上昇が大きかった（小さかった）銘柄群は、その後の一定期間においても相対的な上昇（下落）傾向を持続する」という順相関傾向を示す事象。リバーサル現象は逆相関傾向を示す事象。","position":{"start":{"line":5,"column":1},"end":{"line":5,"column":1}},"key":"dtH9zQeXIR"}],"key":"e4G1Wo1f0o"}],"key":"DCIl7JRK6C"},{"type":"block","kind":"notebook-content","children":[{"type":"heading","depth":3,"position":{"start":{"line":1,"column":1},"end":{"line":1,"column":1}},"children":[{"type":"text","value":"モメンタム・クラッシュ","position":{"start":{"line":1,"column":1},"end":{"line":1,"column":1}},"key":"rz6XN8KYRM"}],"identifier":"id","label":"モメンタム・クラッシュ","html_id":"id-1","implicit":true,"key":"WJZ5XAM5kQ"},{"type":"paragraph","position":{"start":{"line":3,"column":1},"end":{"line":3,"column":1}},"children":[{"type":"text","value":"リーマンショックのようなクラッシュをきっかけに、モメンタムが弱まる現象","position":{"start":{"line":3,"column":1},"end":{"line":3,"column":1}},"key":"N5lEmiqufJ"}],"key":"Gnsajuznfi"},{"type":"list","ordered":false,"spread":false,"position":{"start":{"line":5,"column":1},"end":{"line":6,"column":1}},"children":[{"type":"listItem","spread":true,"position":{"start":{"line":5,"column":1},"end":{"line":5,"column":1}},"children":[{"type":"paragraph","children":[{"type":"link","url":"https://gendai.media/articles/-/52570?page=2","position":{"start":{"line":5,"column":1},"end":{"line":5,"column":1}},"children":[{"type":"text","value":"「順張り投資」のパフォーマンス低下が示唆するもの（安達 誠司） | マネー現代 | 講談社","position":{"start":{"line":5,"column":1},"end":{"line":5,"column":1}},"key":"VBjzO7DPrL"}],"urlSource":"https://gendai.media/articles/-/52570?page=2","key":"DIbYg80Ue7"}],"key":"V1OsZ1NShU"}],"key":"uD9sTaxfiX"},{"type":"listItem","spread":true,"position":{"start":{"line":6,"column":1},"end":{"line":6,"column":1}},"children":[{"type":"paragraph","children":[{"type":"link","url":"https://www.nam.co.jp/market/column/quantstopics/2019/190201_2.html","position":{"start":{"line":6,"column":1},"end":{"line":6,"column":1}},"children":[{"type":"text","value":"クオンツとAI／機械学習の融合（モメンタム／リバーサル概論）2｜吉野貴晶のクオンツトピックス｜投資信託のニッセイアセットマネジメント","position":{"start":{"line":6,"column":1},"end":{"line":6,"column":1}},"key":"HTnNWAWNS2"}],"urlSource":"https://www.nam.co.jp/market/column/quantstopics/2019/190201_2.html","key":"o45kP7Otr3"}],"key":"j6yqnsWGL7"}],"key":"KCuN97FrSE"}],"key":"NsFsuDSIkW"}],"key":"sX2Mg9pOIS"},{"type":"block","kind":"notebook-content","children":[{"type":"heading","depth":2,"position":{"start":{"line":1,"column":1},"end":{"line":1,"column":1}},"children":[{"type":"text","value":"モメンタムの予測","position":{"start":{"line":1,"column":1},"end":{"line":1,"column":1}},"key":"CNDdLZZlbk"}],"identifier":"id","label":"モメンタムの予測","html_id":"id-2","implicit":true,"key":"UHnBlcmjeg"}],"key":"Dtbi7NeR7F"},{"type":"block","kind":"notebook-content","children":[{"type":"card","children":[{"type":"cardTitle","children":[{"type":"text","value":"モメンタム予測","position":{"start":{"line":1,"column":1},"end":{"line":1,"column":1}},"key":"n3uU3tfnlz"}],"key":"ajbMRzzk7r"},{"type":"paragraph","position":{"start":{"line":3,"column":1},"end":{"line":3,"column":1}},"children":[{"type":"link","url":"https://www.nam.co.jp/market/column/quantstopics/2020/200618.html","position":{"start":{"line":3,"column":1},"end":{"line":3,"column":1}},"children":[{"type":"text","value":"NGBoostを用いた市場マクロ変数によるモメンタム効果の将来予測｜吉野貴晶のクオンツトピックス｜投資信託のニッセイアセットマネジメント","position":{"start":{"line":3,"column":1},"end":{"line":3,"column":1}},"key":"ULWcpXwMsf"}],"urlSource":"https://www.nam.co.jp/market/column/quantstopics/2020/200618.html","key":"d7W1hSZuNt"}],"key":"r4ctnokFrw"},{"type":"list","ordered":false,"spread":false,"position":{"start":{"line":5,"column":1},"end":{"line":8,"column":1}},"children":[{"type":"listItem","spread":true,"position":{"start":{"line":5,"column":1},"end":{"line":5,"column":1}},"children":[{"type":"paragraph","children":[{"type":"text","value":"説明変数: 月次の","position":{"start":{"line":5,"column":1},"end":{"line":5,"column":1}},"key":"UjlD1gqgql"},{"type":"link","url":"https://www.nam.co.jp/market/column/quantstopics/2020/200417.html","position":{"start":{"line":5,"column":1},"end":{"line":5,"column":1}},"children":[{"type":"text","value":"市場マクロ変数","position":{"start":{"line":5,"column":1},"end":{"line":5,"column":1}},"key":"ruVjxvGZN4"}],"urlSource":"https://www.nam.co.jp/market/column/quantstopics/2020/200417.html","key":"Ky5jARV1dg"},{"type":"text","value":" 12次元","position":{"start":{"line":5,"column":1},"end":{"line":5,"column":1}},"key":"DXoDuxGNCy"}],"key":"z8hcqrb1dC"}],"key":"OZSfb47xgt"},{"type":"listItem","spread":true,"position":{"start":{"line":6,"column":1},"end":{"line":6,"column":1}},"children":[{"type":"paragraph","children":[{"type":"text","value":"目的変数: 月次モメンタムファクタースプレッドリターン","position":{"start":{"line":6,"column":1},"end":{"line":6,"column":1}},"key":"wrCApgqYJx"}],"key":"crbSxasS8i"}],"key":"J6ooxgvM1v"},{"type":"listItem","spread":true,"position":{"start":{"line":7,"column":1},"end":{"line":7,"column":1}},"children":[{"type":"paragraph","children":[{"type":"text","value":"方策：月次モメンタムファクタースプレッドリターンが0%以上の予測なら買い、未満なら売り","position":{"start":{"line":7,"column":1},"end":{"line":7,"column":1}},"key":"jPbpNp8nTN"}],"key":"p2ITnJxcW1"}],"key":"K2wG6wGSSZ"},{"type":"listItem","spread":true,"position":{"start":{"line":8,"column":1},"end":{"line":8,"column":1}},"children":[{"type":"paragraph","children":[{"type":"text","value":"結果：常に買うよりは累積リターンが多い。正解率54.7%","position":{"start":{"line":8,"column":1},"end":{"line":8,"column":1}},"key":"oaec6GrTym"}],"key":"LAAsmJn3nM"}],"key":"HqH3O0SHzV"}],"key":"EC9sJnu34G"}],"key":"J0pkYumzpn"}],"key":"Y3yu03dG2c"},{"type":"block","kind":"notebook-content","children":[{"type":"card","children":[{"type":"cardTitle","children":[{"type":"text","value":"ファクタースプレッドリターン","position":{"start":{"line":1,"column":1},"end":{"line":1,"column":1}},"key":"kAp5IsLDkP"}],"key":"jiVYYxSPuA"},{"type":"list","ordered":true,"start":1,"spread":false,"position":{"start":{"line":3,"column":1},"end":{"line":4,"column":1}},"children":[{"type":"listItem","spread":true,"position":{"start":{"line":3,"column":1},"end":{"line":3,"column":1}},"children":[{"type":"paragraph","children":[{"type":"text","value":"当月のファクター値（BPR等）に基づいて全銘柄を5個のグループに分ける（等ウェイト）。","position":{"start":{"line":3,"column":1},"end":{"line":3,"column":1}},"key":"MnNTVFxJbE"}],"key":"HRuYB1UlZG"}],"key":"PZXjWrqtsG"},{"type":"listItem","spread":true,"position":{"start":{"line":4,"column":1},"end":{"line":4,"column":1}},"children":[{"type":"paragraph","children":[{"type":"text","value":"その5個のグループにおける、上位1/5と下位1/5に該当するグループの翌月リターンの差の値をファクタースプレッドリターンという","position":{"start":{"line":4,"column":1},"end":{"line":4,"column":1}},"key":"sW8cH7iZAt"}],"key":"uzwdzlbtLj"}],"key":"dKhq7WxDP8"}],"key":"VttvqQrEJn"}],"key":"vqyGrAeTbB"}],"key":"PIJOmJF2VL"}],"key":"D8x4Uou9xn"},"references":{"cite":{"order":[],"data":{}}},"footer":{"navigation":{"prev":{"title":"高配当株ファンド投資","url":"/economics/financial-economics/investment-strategies/high-dividend","group":"経済学"},"next":{"title":"増担保規制空売り","url":"/economics/financial-economics/investment-strategies/regulated-short","group":"経済学"}}},"domain":"http://localhost:3000"}