{"version":3,"kind":"Notebook","sha256":"13ee2d44657eda7688c8ac43766936482dd0697ebc8401f3b647f7b973f84972","slug":"recommender-system.collaborative-filtering","location":"/recommender_system/collaborative_filtering.ipynb","dependencies":[],"frontmatter":{"title":"協調フィルタリング","content_includes_title":false,"kernelspec":{"name":"python3","display_name":"Python 3 (ipykernel)","language":"python"},"authors":[{"nameParsed":{"literal":"mitama","family":"mitama"},"name":"mitama","id":"contributors-myst-generated-uid-0"}],"github":"https://github.com/nigimitama/notes","copyright":"© mitama","numbering":{"title":{"offset":1}},"source_url":"https://github.com/nigimitama/notes/blob/main/book/recommender_system/collaborative_filtering.ipynb","edit_url":"https://github.com/nigimitama/notes/edit/main/book/recommender_system/collaborative_filtering.ipynb","exports":[{"format":"ipynb","filename":"collaborative_filtering.ipynb","url":"/notes/build/collaborative_filter-5acc51ee0fb997b2a52f08ccbcbec500.ipynb"}]},"widgets":{},"mdast":{"type":"root","children":[{"type":"block","kind":"notebook-content","children":[{"type":"paragraph","position":{"start":{"line":3,"column":1},"end":{"line":3,"column":1}},"children":[{"type":"text","value":"協調フィルタリング（Collaborative Filtering）は、ユーザーの行動履歴や評価データから「似ているユーザー／アイテム」を見つけて推薦を行う手法","position":{"start":{"line":3,"column":1},"end":{"line":3,"column":1}},"key":"snSzA1WewH"}],"key":"UEja5V0L1y"},{"type":"paragraph","position":{"start":{"line":5,"column":1},"end":{"line":5,"column":1}},"children":[{"type":"text","value":"基本の考え方自体はシンプルで","position":{"start":{"line":5,"column":1},"end":{"line":5,"column":1}},"key":"m78cqxXTzD"}],"key":"HYFNHj6eGb"},{"type":"list","ordered":false,"spread":false,"position":{"start":{"line":7,"column":1},"end":{"line":9,"column":1}},"children":[{"type":"listItem","spread":true,"position":{"start":{"line":7,"column":1},"end":{"line":7,"column":1}},"children":[{"type":"paragraph","children":[{"type":"text","value":"「あなたと似た行動をしている人が好きなものは、あなたも好きな可能性が高い」","position":{"start":{"line":7,"column":1},"end":{"line":7,"column":1}},"key":"ogyVOG9YdG"}],"key":"V159D9P1zP"}],"key":"GFVYor4XfW"},{"type":"listItem","spread":true,"position":{"start":{"line":8,"column":1},"end":{"line":9,"column":1}},"children":[{"type":"paragraph","children":[{"type":"text","value":"「あなたが好きなアイテムに似たアイテムは、他にも好きになる可能性が高い」","position":{"start":{"line":8,"column":1},"end":{"line":8,"column":1}},"key":"ttqcdyGdKO"}],"key":"hSqWu7ZuOR"}],"key":"hF0YWloIWa"}],"key":"sHWcajgxUA"},{"type":"paragraph","position":{"start":{"line":10,"column":1},"end":{"line":10,"column":1}},"children":[{"type":"text","value":"というもの。","position":{"start":{"line":10,"column":1},"end":{"line":10,"column":1}},"key":"UM7PWvYul2"}],"key":"sASYBuvZ7W"}],"key":"AXuiajQzUi"},{"type":"block","kind":"notebook-content","children":[{"type":"paragraph","position":{"start":{"line":1,"column":1},"end":{"line":1,"column":1}},"children":[{"type":"text","value":"アルゴリズムはメモリベースとモデルベースに大別される","position":{"start":{"line":1,"column":1},"end":{"line":1,"column":1}},"key":"Y7M31fpJaU"}],"key":"hlbLzQFg1c"},{"type":"list","ordered":true,"start":1,"spread":false,"position":{"start":{"line":3,"column":1},"end":{"line":6,"column":1}},"children":[{"type":"listItem","spread":true,"position":{"start":{"line":3,"column":1},"end":{"line":5,"column":1}},"children":[{"type":"paragraph","children":[{"type":"text","value":"メモリベース法（memory-based method, instance-based method）","position":{"start":{"line":3,"column":1},"end":{"line":3,"column":1}},"key":"k8zTYWnrLh"}],"key":"uX084CxXpv"},{"type":"list","ordered":false,"spread":false,"position":{"start":{"line":4,"column":1},"end":{"line":5,"column":1}},"children":[{"type":"listItem","spread":true,"position":{"start":{"line":4,"column":1},"end":{"line":4,"column":1}},"children":[{"type":"paragraph","children":[{"type":"text","value":"ユーザーベース：ユーザの類似性に注目する","position":{"start":{"line":4,"column":1},"end":{"line":4,"column":1}},"key":"TJMGN7wR0C"}],"key":"Vkgk2ruwcJ"}],"key":"TTga5VHpsd"},{"type":"listItem","spread":true,"position":{"start":{"line":5,"column":1},"end":{"line":5,"column":1}},"children":[{"type":"paragraph","children":[{"type":"text","value":"アイテムベース：アイテムの類似性に注目する","position":{"start":{"line":5,"column":1},"end":{"line":5,"column":1}},"key":"XmKsz3ZB2w"}],"key":"OPm1u0iPcv"}],"key":"zWCfpTlevF"}],"key":"Fdob4iF3ZM"}],"key":"bYRhB2Rc5m"},{"type":"listItem","spread":true,"position":{"start":{"line":6,"column":1},"end":{"line":6,"column":1}},"children":[{"type":"paragraph","children":[{"type":"text","value":"モデルベース法（model-based method）：ユーザの嗜好をモデル化して推薦","position":{"start":{"line":6,"column":1},"end":{"line":6,"column":1}},"key":"ZiGbRFJmd1"}],"key":"OU7x5NBysS"}],"key":"ZtuDW42ZcA"}],"key":"jFYqsoE0Zl"}],"key":"gaFYtII9Gi"},{"type":"block","kind":"notebook-content","children":[{"type":"heading","depth":2,"position":{"start":{"line":1,"column":1},"end":{"line":1,"column":1}},"children":[{"type":"text","value":"メモリベース法","position":{"start":{"line":1,"column":1},"end":{"line":1,"column":1}},"key":"rDmMMhiSz9"}],"identifier":"id","label":"メモリベース法","html_id":"id","implicit":true,"key":"G3o5b0xSZz"},{"type":"paragraph","position":{"start":{"line":3,"column":1},"end":{"line":3,"column":1}},"children":[{"type":"text","value":"推薦の都度リアルタイムに類似度を計算する方法は ","position":{"start":{"line":3,"column":1},"end":{"line":3,"column":1}},"key":"weeJCMsX0I"},{"type":"strong","position":{"start":{"line":3,"column":1},"end":{"line":3,"column":1}},"children":[{"type":"text","value":"メモリベース法（memory-based method）","position":{"start":{"line":3,"column":1},"end":{"line":3,"column":1}},"key":"bDnlO1RNDA"}],"key":"Qre13caBMm"},{"type":"text","value":" あるいは ","position":{"start":{"line":3,"column":1},"end":{"line":3,"column":1}},"key":"JbYYyi8UDL"},{"type":"strong","position":{"start":{"line":3,"column":1},"end":{"line":3,"column":1}},"children":[{"type":"text","value":"事例ベース法（instance-based method）","position":{"start":{"line":3,"column":1},"end":{"line":3,"column":1}},"key":"s8kqGfXZLG"}],"key":"dWx4zjdpZ5"},{"type":"text","value":" と呼ばれる。","position":{"start":{"line":3,"column":1},"end":{"line":3,"column":1}},"key":"UlbxvgbWT1"}],"key":"J9CDMN9W6w"},{"type":"heading","depth":3,"position":{"start":{"line":5,"column":1},"end":{"line":5,"column":1}},"children":[{"type":"text","value":"ユーザーベース協調フィルタリング","position":{"start":{"line":5,"column":1},"end":{"line":5,"column":1}},"key":"z3Ls2JzcY2"}],"identifier":"id","label":"ユーザーベース協調フィルタリング","html_id":"id-1","implicit":true,"key":"LkWzxumY2J"},{"type":"paragraph","position":{"start":{"line":7,"column":1},"end":{"line":7,"column":1}},"children":[{"type":"text","value":"ユーザー","position":{"start":{"line":7,"column":1},"end":{"line":7,"column":1}},"key":"mV4NGviO7P"},{"type":"inlineMath","value":"i","position":{"start":{"line":7,"column":1},"end":{"line":7,"column":1}},"html":"<span class=\"katex\"><span class=\"katex-mathml\"><math xmlns=\"http://www.w3.org/1998/Math/MathML\"><semantics><mrow><mi>i</mi></mrow><annotation encoding=\"application/x-tex\">i</annotation></semantics></math></span><span class=\"katex-html\" aria-hidden=\"true\"><span class=\"base\"><span class=\"strut\" style=\"height:0.6595em;\"></span><span class=\"mord mathnormal\">i</span></span></span></span>","key":"EpymttYrRg"},{"type":"text","value":"と似たユーザーがアイテム","position":{"start":{"line":7,"column":1},"end":{"line":7,"column":1}},"key":"fP993Oqqn6"},{"type":"inlineMath","value":"j","position":{"start":{"line":7,"column":1},"end":{"line":7,"column":1}},"html":"<span class=\"katex\"><span class=\"katex-mathml\"><math xmlns=\"http://www.w3.org/1998/Math/MathML\"><semantics><mrow><mi>j</mi></mrow><annotation encoding=\"application/x-tex\">j</annotation></semantics></math></span><span class=\"katex-html\" aria-hidden=\"true\"><span class=\"base\"><span class=\"strut\" style=\"height:0.854em;vertical-align:-0.1944em;\"></span><span class=\"mord mathnormal\" style=\"margin-right:0.05724em;\">j</span></span></span></span>","key":"zEup9xx2X7"},{"type":"text","value":"に与えた評価に基づいて、ユーザー","position":{"start":{"line":7,"column":1},"end":{"line":7,"column":1}},"key":"fh3LTXx1Xq"},{"type":"inlineMath","value":"i","position":{"start":{"line":7,"column":1},"end":{"line":7,"column":1}},"html":"<span class=\"katex\"><span class=\"katex-mathml\"><math xmlns=\"http://www.w3.org/1998/Math/MathML\"><semantics><mrow><mi>i</mi></mrow><annotation encoding=\"application/x-tex\">i</annotation></semantics></math></span><span class=\"katex-html\" aria-hidden=\"true\"><span class=\"base\"><span class=\"strut\" style=\"height:0.6595em;\"></span><span class=\"mord mathnormal\">i</span></span></span></span>","key":"dqPBBlVvNL"},{"type":"text","value":"がまだ評価していないアイテム","position":{"start":{"line":7,"column":1},"end":{"line":7,"column":1}},"key":"v0npH2qoXy"},{"type":"inlineMath","value":"j","position":{"start":{"line":7,"column":1},"end":{"line":7,"column":1}},"html":"<span class=\"katex\"><span class=\"katex-mathml\"><math xmlns=\"http://www.w3.org/1998/Math/MathML\"><semantics><mrow><mi>j</mi></mrow><annotation encoding=\"application/x-tex\">j</annotation></semantics></math></span><span class=\"katex-html\" aria-hidden=\"true\"><span class=\"base\"><span class=\"strut\" style=\"height:0.854em;vertical-align:-0.1944em;\"></span><span class=\"mord mathnormal\" style=\"margin-right:0.05724em;\">j</span></span></span></span>","key":"CQkodRDNEC"},{"type":"text","value":"に与えるレイティング（またはscore）","position":{"start":{"line":7,"column":1},"end":{"line":7,"column":1}},"key":"n8Qjoyd2XZ"},{"type":"inlineMath","value":"s_{ij}","position":{"start":{"line":7,"column":1},"end":{"line":7,"column":1}},"html":"<span class=\"katex\"><span class=\"katex-mathml\"><math xmlns=\"http://www.w3.org/1998/Math/MathML\"><semantics><mrow><msub><mi>s</mi><mrow><mi>i</mi><mi>j</mi></mrow></msub></mrow><annotation encoding=\"application/x-tex\">s_{ij}</annotation></semantics></math></span><span class=\"katex-html\" aria-hidden=\"true\"><span class=\"base\"><span class=\"strut\" style=\"height:0.7167em;vertical-align:-0.2861em;\"></span><span class=\"mord\"><span class=\"mord mathnormal\">s</span><span class=\"msupsub\"><span class=\"vlist-t vlist-t2\"><span class=\"vlist-r\"><span class=\"vlist\" style=\"height:0.3117em;\"><span style=\"top:-2.55em;margin-left:0em;margin-right:0.05em;\"><span class=\"pstrut\" style=\"height:2.7em;\"></span><span class=\"sizing reset-size6 size3 mtight\"><span class=\"mord mtight\"><span class=\"mord mathnormal mtight\" style=\"margin-right:0.05724em;\">ij</span></span></span></span></span><span class=\"vlist-s\">​</span></span><span class=\"vlist-r\"><span class=\"vlist\" style=\"height:0.2861em;\"><span></span></span></span></span></span></span></span></span></span>","key":"Bys6ldnRuQ"},{"type":"text","value":"を予測する","position":{"start":{"line":7,"column":1},"end":{"line":7,"column":1}},"key":"ulIQOYps0T"}],"key":"lHwzAWIyAA"},{"type":"math","value":"s_{i j}=\\bar{y}_{i \\cdot}+\\frac{\\sum_{\\ell \\in \\mathcal{I}_j(i)} w(i, \\ell)\\left(y_{\\ell j}-\\bar{y}_{\\ell .}\\right)}{\\sum_{\\ell \\in \\mathcal{I}_j(i)}|w(i, \\ell)|}","position":{"start":{"line":9,"column":1},"end":{"line":11,"column":1}},"html":"<span class=\"katex-display\"><span class=\"katex\"><span class=\"katex-mathml\"><math xmlns=\"http://www.w3.org/1998/Math/MathML\" display=\"block\"><semantics><mrow><msub><mi>s</mi><mrow><mi>i</mi><mi>j</mi></mrow></msub><mo>=</mo><msub><mover accent=\"true\"><mi>y</mi><mo>ˉ</mo></mover><mrow><mi>i</mi><mo>⋅</mo></mrow></msub><mo>+</mo><mfrac><mrow><munder><mo>∑</mo><mrow><mi mathvariant=\"normal\">ℓ</mi><mo>∈</mo><msub><mi mathvariant=\"script\">I</mi><mi>j</mi></msub><mo stretchy=\"false\">(</mo><mi>i</mi><mo stretchy=\"false\">)</mo></mrow></munder><mi>w</mi><mo stretchy=\"false\">(</mo><mi>i</mi><mo separator=\"true\">,</mo><mi mathvariant=\"normal\">ℓ</mi><mo stretchy=\"false\">)</mo><mrow><mo fence=\"true\">(</mo><msub><mi>y</mi><mrow><mi mathvariant=\"normal\">ℓ</mi><mi>j</mi></mrow></msub><mo>−</mo><msub><mover accent=\"true\"><mi>y</mi><mo>ˉ</mo></mover><mrow><mi mathvariant=\"normal\">ℓ</mi><mi mathvariant=\"normal\">.</mi></mrow></msub><mo fence=\"true\">)</mo></mrow></mrow><mrow><munder><mo>∑</mo><mrow><mi mathvariant=\"normal\">ℓ</mi><mo>∈</mo><msub><mi mathvariant=\"script\">I</mi><mi>j</mi></msub><mo stretchy=\"false\">(</mo><mi>i</mi><mo stretchy=\"false\">)</mo></mrow></munder><mi mathvariant=\"normal\">∣</mi><mi>w</mi><mo stretchy=\"false\">(</mo><mi>i</mi><mo separator=\"true\">,</mo><mi mathvariant=\"normal\">ℓ</mi><mo stretchy=\"false\">)</mo><mi mathvariant=\"normal\">∣</mi></mrow></mfrac></mrow><annotation encoding=\"application/x-tex\">s_{i j}=\\bar{y}_{i \\cdot}+\\frac{\\sum_{\\ell \\in \\mathcal{I}_j(i)} w(i, \\ell)\\left(y_{\\ell j}-\\bar{y}_{\\ell .}\\right)}{\\sum_{\\ell \\in \\mathcal{I}_j(i)}|w(i, \\ell)|}</annotation></semantics></math></span><span class=\"katex-html\" aria-hidden=\"true\"><span class=\"base\"><span class=\"strut\" style=\"height:0.7167em;vertical-align:-0.2861em;\"></span><span class=\"mord\"><span class=\"mord mathnormal\">s</span><span class=\"msupsub\"><span class=\"vlist-t vlist-t2\"><span class=\"vlist-r\"><span class=\"vlist\" style=\"height:0.3117em;\"><span style=\"top:-2.55em;margin-left:0em;margin-right:0.05em;\"><span class=\"pstrut\" style=\"height:2.7em;\"></span><span class=\"sizing reset-size6 size3 mtight\"><span class=\"mord mtight\"><span class=\"mord mathnormal mtight\" style=\"margin-right:0.05724em;\">ij</span></span></span></span></span><span class=\"vlist-s\">​</span></span><span class=\"vlist-r\"><span class=\"vlist\" style=\"height:0.2861em;\"><span></span></span></span></span></span></span><span class=\"mspace\" style=\"margin-right:0.2778em;\"></span><span class=\"mrel\">=</span><span class=\"mspace\" style=\"margin-right:0.2778em;\"></span></span><span class=\"base\"><span class=\"strut\" style=\"height:0.7778em;vertical-align:-0.1944em;\"></span><span class=\"mord\"><span class=\"mord accent\"><span class=\"vlist-t vlist-t2\"><span class=\"vlist-r\"><span class=\"vlist\" style=\"height:0.5678em;\"><span style=\"top:-3em;\"><span class=\"pstrut\" style=\"height:3em;\"></span><span class=\"mord mathnormal\" style=\"margin-right:0.03588em;\">y</span></span><span style=\"top:-3em;\"><span class=\"pstrut\" style=\"height:3em;\"></span><span class=\"accent-body\" style=\"left:-0.1944em;\"><span class=\"mord\">ˉ</span></span></span></span><span class=\"vlist-s\">​</span></span><span class=\"vlist-r\"><span class=\"vlist\" style=\"height:0.1944em;\"><span></span></span></span></span></span><span class=\"msupsub\"><span class=\"vlist-t vlist-t2\"><span class=\"vlist-r\"><span class=\"vlist\" style=\"height:0.3117em;\"><span style=\"top:-2.55em;margin-left:-0.0359em;margin-right:0.05em;\"><span class=\"pstrut\" style=\"height:2.7em;\"></span><span class=\"sizing reset-size6 size3 mtight\"><span class=\"mord mtight\"><span class=\"mord mathnormal mtight\">i</span><span class=\"mord mtight\">⋅</span></span></span></span></span><span class=\"vlist-s\">​</span></span><span class=\"vlist-r\"><span class=\"vlist\" style=\"height:0.15em;\"><span></span></span></span></span></span></span><span class=\"mspace\" style=\"margin-right:0.2222em;\"></span><span class=\"mbin\">+</span><span class=\"mspace\" style=\"margin-right:0.2222em;\"></span></span><span class=\"base\"><span class=\"strut\" style=\"height:2.8201em;vertical-align:-1.183em;\"></span><span class=\"mord\"><span class=\"mopen nulldelimiter\"></span><span class=\"mfrac\"><span class=\"vlist-t vlist-t2\"><span class=\"vlist-r\"><span class=\"vlist\" style=\"height:1.637em;\"><span style=\"top:-2.314em;\"><span class=\"pstrut\" style=\"height:3em;\"></span><span class=\"mord\"><span class=\"mop\"><span class=\"mop op-symbol small-op\" style=\"position:relative;top:0em;\">∑</span><span class=\"msupsub\"><span class=\"vlist-t vlist-t2\"><span class=\"vlist-r\"><span class=\"vlist\" style=\"height:0.2253em;\"><span style=\"top:-2.4003em;margin-left:0em;margin-right:0.05em;\"><span class=\"pstrut\" style=\"height:2.7em;\"></span><span class=\"sizing reset-size6 size3 mtight\"><span class=\"mord mtight\"><span class=\"mord mtight\">ℓ</span><span class=\"mrel mtight\">∈</span><span class=\"mord mtight\"><span class=\"mord mathcal mtight\" style=\"margin-right:0.07382em;\">I</span><span class=\"msupsub\"><span class=\"vlist-t vlist-t2\"><span class=\"vlist-r\"><span class=\"vlist\" style=\"height:0.3281em;\"><span style=\"top:-2.357em;margin-left:-0.0738em;margin-right:0.0714em;\"><span class=\"pstrut\" style=\"height:2.5em;\"></span><span class=\"sizing reset-size3 size1 mtight\"><span class=\"mord mathnormal mtight\" style=\"margin-right:0.05724em;\">j</span></span></span></span><span class=\"vlist-s\">​</span></span><span class=\"vlist-r\"><span class=\"vlist\" style=\"height:0.2819em;\"><span></span></span></span></span></span></span><span class=\"mopen mtight\">(</span><span class=\"mord mathnormal mtight\">i</span><span class=\"mclose mtight\">)</span></span></span></span></span><span class=\"vlist-s\">​</span></span><span class=\"vlist-r\"><span class=\"vlist\" style=\"height:0.497em;\"><span></span></span></span></span></span></span><span class=\"mspace\" style=\"margin-right:0.1667em;\"></span><span class=\"mord\">∣</span><span class=\"mord mathnormal\" style=\"margin-right:0.02691em;\">w</span><span class=\"mopen\">(</span><span class=\"mord mathnormal\">i</span><span class=\"mpunct\">,</span><span class=\"mspace\" style=\"margin-right:0.1667em;\"></span><span class=\"mord\">ℓ</span><span class=\"mclose\">)</span><span class=\"mord\">∣</span></span></span><span style=\"top:-3.23em;\"><span class=\"pstrut\" style=\"height:3em;\"></span><span class=\"frac-line\" style=\"border-bottom-width:0.04em;\"></span></span><span style=\"top:-3.887em;\"><span class=\"pstrut\" style=\"height:3em;\"></span><span class=\"mord\"><span class=\"mop\"><span class=\"mop op-symbol small-op\" style=\"position:relative;top:0em;\">∑</span><span class=\"msupsub\"><span class=\"vlist-t vlist-t2\"><span class=\"vlist-r\"><span class=\"vlist\" style=\"height:0.2253em;\"><span style=\"top:-2.4003em;margin-left:0em;margin-right:0.05em;\"><span class=\"pstrut\" style=\"height:2.7em;\"></span><span class=\"sizing reset-size6 size3 mtight\"><span class=\"mord mtight\"><span class=\"mord mtight\">ℓ</span><span class=\"mrel mtight\">∈</span><span class=\"mord mtight\"><span class=\"mord mathcal mtight\" style=\"margin-right:0.07382em;\">I</span><span class=\"msupsub\"><span class=\"vlist-t vlist-t2\"><span class=\"vlist-r\"><span class=\"vlist\" style=\"height:0.3281em;\"><span style=\"top:-2.357em;margin-left:-0.0738em;margin-right:0.0714em;\"><span class=\"pstrut\" style=\"height:2.5em;\"></span><span class=\"sizing reset-size3 size1 mtight\"><span class=\"mord mathnormal mtight\" style=\"margin-right:0.05724em;\">j</span></span></span></span><span class=\"vlist-s\">​</span></span><span class=\"vlist-r\"><span class=\"vlist\" style=\"height:0.2819em;\"><span></span></span></span></span></span></span><span class=\"mopen mtight\">(</span><span class=\"mord mathnormal mtight\">i</span><span class=\"mclose mtight\">)</span></span></span></span></span><span class=\"vlist-s\">​</span></span><span class=\"vlist-r\"><span class=\"vlist\" style=\"height:0.497em;\"><span></span></span></span></span></span></span><span class=\"mspace\" style=\"margin-right:0.1667em;\"></span><span class=\"mord mathnormal\" style=\"margin-right:0.02691em;\">w</span><span class=\"mopen\">(</span><span class=\"mord mathnormal\">i</span><span class=\"mpunct\">,</span><span class=\"mspace\" style=\"margin-right:0.1667em;\"></span><span class=\"mord\">ℓ</span><span class=\"mclose\">)</span><span class=\"mspace\" style=\"margin-right:0.1667em;\"></span><span class=\"minner\"><span class=\"mopen delimcenter\" style=\"top:0em;\">(</span><span class=\"mord\"><span class=\"mord mathnormal\" style=\"margin-right:0.03588em;\">y</span><span class=\"msupsub\"><span class=\"vlist-t vlist-t2\"><span class=\"vlist-r\"><span class=\"vlist\" style=\"height:0.3361em;\"><span style=\"top:-2.55em;margin-left:-0.0359em;margin-right:0.05em;\"><span class=\"pstrut\" style=\"height:2.7em;\"></span><span class=\"sizing reset-size6 size3 mtight\"><span class=\"mord mtight\"><span class=\"mord mtight\">ℓ</span><span class=\"mord mathnormal mtight\" style=\"margin-right:0.05724em;\">j</span></span></span></span></span><span class=\"vlist-s\">​</span></span><span class=\"vlist-r\"><span class=\"vlist\" style=\"height:0.2861em;\"><span></span></span></span></span></span></span><span class=\"mspace\" style=\"margin-right:0.2222em;\"></span><span class=\"mbin\">−</span><span class=\"mspace\" style=\"margin-right:0.2222em;\"></span><span class=\"mord\"><span class=\"mord accent\"><span class=\"vlist-t vlist-t2\"><span class=\"vlist-r\"><span class=\"vlist\" style=\"height:0.5678em;\"><span style=\"top:-3em;\"><span class=\"pstrut\" style=\"height:3em;\"></span><span class=\"mord mathnormal\" style=\"margin-right:0.03588em;\">y</span></span><span style=\"top:-3em;\"><span class=\"pstrut\" style=\"height:3em;\"></span><span class=\"accent-body\" style=\"left:-0.1944em;\"><span class=\"mord\">ˉ</span></span></span></span><span class=\"vlist-s\">​</span></span><span class=\"vlist-r\"><span class=\"vlist\" style=\"height:0.1944em;\"><span></span></span></span></span></span><span class=\"msupsub\"><span class=\"vlist-t vlist-t2\"><span class=\"vlist-r\"><span class=\"vlist\" style=\"height:0.3361em;\"><span style=\"top:-2.55em;margin-left:-0.0359em;margin-right:0.05em;\"><span class=\"pstrut\" style=\"height:2.7em;\"></span><span class=\"sizing reset-size6 size3 mtight\"><span class=\"mord mtight\"><span class=\"mord mtight\">ℓ</span><span class=\"mord mtight\">.</span></span></span></span></span><span class=\"vlist-s\">​</span></span><span class=\"vlist-r\"><span class=\"vlist\" style=\"height:0.15em;\"><span></span></span></span></span></span></span><span class=\"mclose delimcenter\" style=\"top:0em;\">)</span></span></span></span></span><span class=\"vlist-s\">​</span></span><span class=\"vlist-r\"><span class=\"vlist\" style=\"height:1.183em;\"><span></span></span></span></span></span><span class=\"mclose nulldelimiter\"></span></span></span></span></span></span>","enumerator":"1","key":"ayVHBRrHHs"},{"type":"list","ordered":false,"spread":false,"position":{"start":{"line":13,"column":1},"end":{"line":17,"column":1}},"children":[{"type":"listItem","spread":true,"position":{"start":{"line":13,"column":1},"end":{"line":13,"column":1}},"children":[{"type":"paragraph","children":[{"type":"inlineMath","value":"\\mathcal{I}_j(i)","position":{"start":{"line":13,"column":1},"end":{"line":13,"column":1}},"html":"<span class=\"katex\"><span class=\"katex-mathml\"><math xmlns=\"http://www.w3.org/1998/Math/MathML\"><semantics><mrow><msub><mi mathvariant=\"script\">I</mi><mi>j</mi></msub><mo stretchy=\"false\">(</mo><mi>i</mi><mo stretchy=\"false\">)</mo></mrow><annotation encoding=\"application/x-tex\">\\mathcal{I}_j(i)</annotation></semantics></math></span><span class=\"katex-html\" aria-hidden=\"true\"><span class=\"base\"><span class=\"strut\" style=\"height:1.0361em;vertical-align:-0.2861em;\"></span><span class=\"mord\"><span class=\"mord mathcal\" style=\"margin-right:0.07382em;\">I</span><span class=\"msupsub\"><span class=\"vlist-t vlist-t2\"><span class=\"vlist-r\"><span class=\"vlist\" style=\"height:0.3117em;\"><span style=\"top:-2.55em;margin-left:-0.0738em;margin-right:0.05em;\"><span class=\"pstrut\" style=\"height:2.7em;\"></span><span class=\"sizing reset-size6 size3 mtight\"><span class=\"mord mathnormal mtight\" style=\"margin-right:0.05724em;\">j</span></span></span></span><span class=\"vlist-s\">​</span></span><span class=\"vlist-r\"><span class=\"vlist\" style=\"height:0.2861em;\"><span></span></span></span></span></span></span><span class=\"mopen\">(</span><span class=\"mord mathnormal\">i</span><span class=\"mclose\">)</span></span></span></span>","key":"cmbpPwOBne"},{"type":"text","value":" ：アイテム ","position":{"start":{"line":13,"column":1},"end":{"line":13,"column":1}},"key":"nrlo20TNr0"},{"type":"inlineMath","value":"j","position":{"start":{"line":13,"column":1},"end":{"line":13,"column":1}},"html":"<span class=\"katex\"><span class=\"katex-mathml\"><math xmlns=\"http://www.w3.org/1998/Math/MathML\"><semantics><mrow><mi>j</mi></mrow><annotation encoding=\"application/x-tex\">j</annotation></semantics></math></span><span class=\"katex-html\" aria-hidden=\"true\"><span class=\"base\"><span class=\"strut\" style=\"height:0.854em;vertical-align:-0.1944em;\"></span><span class=\"mord mathnormal\" style=\"margin-right:0.05724em;\">j</span></span></span></span>","key":"qKWoZYHGza"},{"type":"text","value":" を評価したユーザでユーザ ","position":{"start":{"line":13,"column":1},"end":{"line":13,"column":1}},"key":"DVAFEidYnJ"},{"type":"inlineMath","value":"i","position":{"start":{"line":13,"column":1},"end":{"line":13,"column":1}},"html":"<span class=\"katex\"><span class=\"katex-mathml\"><math xmlns=\"http://www.w3.org/1998/Math/MathML\"><semantics><mrow><mi>i</mi></mrow><annotation encoding=\"application/x-tex\">i</annotation></semantics></math></span><span class=\"katex-html\" aria-hidden=\"true\"><span class=\"base\"><span class=\"strut\" style=\"height:0.6595em;\"></span><span class=\"mord mathnormal\">i</span></span></span></span>","key":"zs1HQT5GgF"},{"type":"text","value":" に類似するユーザの集合","position":{"start":{"line":13,"column":1},"end":{"line":13,"column":1}},"key":"LD0ThLRXwx"}],"key":"dBPrwqvSYg"}],"key":"oEHyYPhLL3"},{"type":"listItem","spread":true,"position":{"start":{"line":14,"column":1},"end":{"line":14,"column":1}},"children":[{"type":"paragraph","children":[{"type":"inlineMath","value":"w(i, \\ell)","position":{"start":{"line":14,"column":1},"end":{"line":14,"column":1}},"html":"<span class=\"katex\"><span class=\"katex-mathml\"><math xmlns=\"http://www.w3.org/1998/Math/MathML\"><semantics><mrow><mi>w</mi><mo stretchy=\"false\">(</mo><mi>i</mi><mo separator=\"true\">,</mo><mi mathvariant=\"normal\">ℓ</mi><mo stretchy=\"false\">)</mo></mrow><annotation encoding=\"application/x-tex\">w(i, \\ell)</annotation></semantics></math></span><span class=\"katex-html\" aria-hidden=\"true\"><span class=\"base\"><span class=\"strut\" style=\"height:1em;vertical-align:-0.25em;\"></span><span class=\"mord mathnormal\" style=\"margin-right:0.02691em;\">w</span><span class=\"mopen\">(</span><span class=\"mord mathnormal\">i</span><span class=\"mpunct\">,</span><span class=\"mspace\" style=\"margin-right:0.1667em;\"></span><span class=\"mord\">ℓ</span><span class=\"mclose\">)</span></span></span></span>","key":"t5QhQuuF4E"},{"type":"text","value":"：ユーザ","position":{"start":{"line":14,"column":1},"end":{"line":14,"column":1}},"key":"mHSnuaaGh8"},{"type":"inlineMath","value":"\\ell","position":{"start":{"line":14,"column":1},"end":{"line":14,"column":1}},"html":"<span class=\"katex\"><span class=\"katex-mathml\"><math xmlns=\"http://www.w3.org/1998/Math/MathML\"><semantics><mrow><mi mathvariant=\"normal\">ℓ</mi></mrow><annotation encoding=\"application/x-tex\">\\ell</annotation></semantics></math></span><span class=\"katex-html\" aria-hidden=\"true\"><span class=\"base\"><span class=\"strut\" style=\"height:0.6944em;\"></span><span class=\"mord\">ℓ</span></span></span></span>","key":"Y3T5LVn5pU"},{"type":"text","value":"の評価に対する重み","position":{"start":{"line":14,"column":1},"end":{"line":14,"column":1}},"key":"ZKcrOHhQQ0"}],"key":"MjGCLczhTa"}],"key":"X4T9gWXALg"},{"type":"listItem","spread":true,"position":{"start":{"line":15,"column":1},"end":{"line":17,"column":1}},"children":[{"type":"paragraph","children":[{"type":"inlineMath","value":"\\bar{y}_{i \\cdot}","position":{"start":{"line":15,"column":1},"end":{"line":15,"column":1}},"html":"<span class=\"katex\"><span class=\"katex-mathml\"><math xmlns=\"http://www.w3.org/1998/Math/MathML\"><semantics><mrow><msub><mover accent=\"true\"><mi>y</mi><mo>ˉ</mo></mover><mrow><mi>i</mi><mo>⋅</mo></mrow></msub></mrow><annotation encoding=\"application/x-tex\">\\bar{y}_{i \\cdot}</annotation></semantics></math></span><span class=\"katex-html\" aria-hidden=\"true\"><span class=\"base\"><span class=\"strut\" style=\"height:0.7622em;vertical-align:-0.1944em;\"></span><span class=\"mord\"><span class=\"mord accent\"><span class=\"vlist-t vlist-t2\"><span class=\"vlist-r\"><span class=\"vlist\" style=\"height:0.5678em;\"><span style=\"top:-3em;\"><span class=\"pstrut\" style=\"height:3em;\"></span><span class=\"mord mathnormal\" style=\"margin-right:0.03588em;\">y</span></span><span style=\"top:-3em;\"><span class=\"pstrut\" style=\"height:3em;\"></span><span class=\"accent-body\" style=\"left:-0.1944em;\"><span class=\"mord\">ˉ</span></span></span></span><span class=\"vlist-s\">​</span></span><span class=\"vlist-r\"><span class=\"vlist\" style=\"height:0.1944em;\"><span></span></span></span></span></span><span class=\"msupsub\"><span class=\"vlist-t vlist-t2\"><span class=\"vlist-r\"><span class=\"vlist\" style=\"height:0.3117em;\"><span style=\"top:-2.55em;margin-left:-0.0359em;margin-right:0.05em;\"><span class=\"pstrut\" style=\"height:2.7em;\"></span><span class=\"sizing reset-size6 size3 mtight\"><span class=\"mord mtight\"><span class=\"mord mathnormal mtight\">i</span><span class=\"mord mtight\">⋅</span></span></span></span></span><span class=\"vlist-s\">​</span></span><span class=\"vlist-r\"><span class=\"vlist\" style=\"height:0.15em;\"><span></span></span></span></span></span></span></span></span></span>","key":"Nw9djNhlQZ"},{"type":"text","value":"はユーザ","position":{"start":{"line":15,"column":1},"end":{"line":15,"column":1}},"key":"pwtPF0m0Xu"},{"type":"inlineMath","value":"i","position":{"start":{"line":15,"column":1},"end":{"line":15,"column":1}},"html":"<span class=\"katex\"><span class=\"katex-mathml\"><math xmlns=\"http://www.w3.org/1998/Math/MathML\"><semantics><mrow><mi>i</mi></mrow><annotation encoding=\"application/x-tex\">i</annotation></semantics></math></span><span class=\"katex-html\" aria-hidden=\"true\"><span class=\"base\"><span class=\"strut\" style=\"height:0.6595em;\"></span><span class=\"mord mathnormal\">i</span></span></span></span>","key":"NitfCWtzo0"},{"type":"text","value":"の他のアイテムへの平均レイティング","position":{"start":{"line":15,"column":1},"end":{"line":15,"column":1}},"key":"teVNg19vui"}],"key":"Mv6ZH5h8ZE"}],"key":"S6qra2v6Oe"}],"key":"D9DFwAsFTC"},{"type":"paragraph","position":{"start":{"line":18,"column":1},"end":{"line":18,"column":1}},"children":[{"type":"text","value":"ユーザ ","position":{"start":{"line":18,"column":1},"end":{"line":18,"column":1}},"key":"ZG0yDETps9"},{"type":"inlineMath","value":"i","position":{"start":{"line":18,"column":1},"end":{"line":18,"column":1}},"html":"<span class=\"katex\"><span class=\"katex-mathml\"><math xmlns=\"http://www.w3.org/1998/Math/MathML\"><semantics><mrow><mi>i</mi></mrow><annotation encoding=\"application/x-tex\">i</annotation></semantics></math></span><span class=\"katex-html\" aria-hidden=\"true\"><span class=\"base\"><span class=\"strut\" style=\"height:0.6595em;\"></span><span class=\"mord mathnormal\">i</span></span></span></span>","key":"d4LfqnLWC4"},{"type":"text","value":" に類似するユーザの集合を定義する方法は、最も単純なのはピアソンの相関係数を使って近傍の","position":{"start":{"line":18,"column":1},"end":{"line":18,"column":1}},"key":"Quz8YvvblO"},{"type":"inlineMath","value":"k","position":{"start":{"line":18,"column":1},"end":{"line":18,"column":1}},"html":"<span class=\"katex\"><span class=\"katex-mathml\"><math xmlns=\"http://www.w3.org/1998/Math/MathML\"><semantics><mrow><mi>k</mi></mrow><annotation encoding=\"application/x-tex\">k</annotation></semantics></math></span><span class=\"katex-html\" aria-hidden=\"true\"><span class=\"base\"><span class=\"strut\" style=\"height:0.6944em;\"></span><span class=\"mord mathnormal\" style=\"margin-right:0.03148em;\">k</span></span></span></span>","key":"WelHrXfaAR"},{"type":"text","value":"人を選択するもの","position":{"start":{"line":18,"column":1},"end":{"line":18,"column":1}},"key":"uIMlCsSbKw"}],"key":"C0IgoJrQgU"}],"key":"BhMt5qbOdi"},{"type":"block","kind":"notebook-content","children":[{"type":"heading","depth":3,"position":{"start":{"line":1,"column":1},"end":{"line":1,"column":1}},"children":[{"type":"text","value":"アイテムベース協調フィルタリング","position":{"start":{"line":1,"column":1},"end":{"line":1,"column":1}},"key":"zEqUprwYi0"}],"identifier":"id","label":"アイテムベース協調フィルタリング","html_id":"id-2","implicit":true,"key":"Igr1OjMTtr"},{"type":"paragraph","position":{"start":{"line":3,"column":1},"end":{"line":4,"column":1}},"children":[{"type":"text","value":"ユーザー","position":{"start":{"line":3,"column":1},"end":{"line":3,"column":1}},"key":"FrfQ8hK9p1"},{"type":"inlineMath","value":"i","position":{"start":{"line":3,"column":1},"end":{"line":3,"column":1}},"html":"<span class=\"katex\"><span class=\"katex-mathml\"><math xmlns=\"http://www.w3.org/1998/Math/MathML\"><semantics><mrow><mi>i</mi></mrow><annotation encoding=\"application/x-tex\">i</annotation></semantics></math></span><span class=\"katex-html\" aria-hidden=\"true\"><span class=\"base\"><span class=\"strut\" style=\"height:0.6595em;\"></span><span class=\"mord mathnormal\">i</span></span></span></span>","key":"KP4GZ5gi9m"},{"type":"text","value":"へのアイテム","position":{"start":{"line":3,"column":1},"end":{"line":3,"column":1}},"key":"AviEH4bcao"},{"type":"inlineMath","value":"j","position":{"start":{"line":3,"column":1},"end":{"line":3,"column":1}},"html":"<span class=\"katex\"><span class=\"katex-mathml\"><math xmlns=\"http://www.w3.org/1998/Math/MathML\"><semantics><mrow><mi>j</mi></mrow><annotation encoding=\"application/x-tex\">j</annotation></semantics></math></span><span class=\"katex-html\" aria-hidden=\"true\"><span class=\"base\"><span class=\"strut\" style=\"height:0.854em;vertical-align:-0.1944em;\"></span><span class=\"mord mathnormal\" style=\"margin-right:0.05724em;\">j</span></span></span></span>","key":"F9dOdknt5L"},{"type":"text","value":"の推薦に使うスコア","position":{"start":{"line":3,"column":1},"end":{"line":3,"column":1}},"key":"Jn5aLvCiEx"},{"type":"inlineMath","value":"\\hat{y}_{ij}","position":{"start":{"line":3,"column":1},"end":{"line":3,"column":1}},"html":"<span class=\"katex\"><span class=\"katex-mathml\"><math xmlns=\"http://www.w3.org/1998/Math/MathML\"><semantics><mrow><msub><mover accent=\"true\"><mi>y</mi><mo>^</mo></mover><mrow><mi>i</mi><mi>j</mi></mrow></msub></mrow><annotation encoding=\"application/x-tex\">\\hat{y}_{ij}</annotation></semantics></math></span><span class=\"katex-html\" aria-hidden=\"true\"><span class=\"base\"><span class=\"strut\" style=\"height:0.9805em;vertical-align:-0.2861em;\"></span><span class=\"mord\"><span class=\"mord accent\"><span class=\"vlist-t vlist-t2\"><span class=\"vlist-r\"><span class=\"vlist\" style=\"height:0.6944em;\"><span style=\"top:-3em;\"><span class=\"pstrut\" style=\"height:3em;\"></span><span class=\"mord mathnormal\" style=\"margin-right:0.03588em;\">y</span></span><span style=\"top:-3em;\"><span class=\"pstrut\" style=\"height:3em;\"></span><span class=\"accent-body\" style=\"left:-0.1944em;\"><span class=\"mord\">^</span></span></span></span><span class=\"vlist-s\">​</span></span><span class=\"vlist-r\"><span class=\"vlist\" style=\"height:0.1944em;\"><span></span></span></span></span></span><span class=\"msupsub\"><span class=\"vlist-t vlist-t2\"><span class=\"vlist-r\"><span class=\"vlist\" style=\"height:0.3117em;\"><span style=\"top:-2.55em;margin-left:-0.0359em;margin-right:0.05em;\"><span class=\"pstrut\" style=\"height:2.7em;\"></span><span class=\"sizing reset-size6 size3 mtight\"><span class=\"mord mtight\"><span class=\"mord mathnormal mtight\" style=\"margin-right:0.05724em;\">ij</span></span></span></span></span><span class=\"vlist-s\">​</span></span><span class=\"vlist-r\"><span class=\"vlist\" style=\"height:0.2861em;\"><span></span></span></span></span></span></span></span></span></span>","key":"rro8UXztnS"},{"type":"text","value":"の推薦について、","position":{"start":{"line":3,"column":1},"end":{"line":3,"column":1}},"key":"q2KI8uUro4"},{"type":"break","position":{"start":{"line":3,"column":1},"end":{"line":3,"column":1}},"key":"YicAKhmpr9"},{"type":"text","value":"あるアイテム","position":{"start":{"line":3,"column":1},"end":{"line":3,"column":1}},"key":"XIN0Emdfua"},{"type":"inlineMath","value":"j","position":{"start":{"line":3,"column":1},"end":{"line":3,"column":1}},"html":"<span class=\"katex\"><span class=\"katex-mathml\"><math xmlns=\"http://www.w3.org/1998/Math/MathML\"><semantics><mrow><mi>j</mi></mrow><annotation encoding=\"application/x-tex\">j</annotation></semantics></math></span><span class=\"katex-html\" aria-hidden=\"true\"><span class=\"base\"><span class=\"strut\" style=\"height:0.854em;vertical-align:-0.1944em;\"></span><span class=\"mord mathnormal\" style=\"margin-right:0.05724em;\">j</span></span></span></span>","key":"oKN0KPhfFL"},{"type":"text","value":"に似ているアイテムたちへのユーザー","position":{"start":{"line":3,"column":1},"end":{"line":3,"column":1}},"key":"DlnBwA0W5U"},{"type":"inlineMath","value":"i","position":{"start":{"line":3,"column":1},"end":{"line":3,"column":1}},"html":"<span class=\"katex\"><span class=\"katex-mathml\"><math xmlns=\"http://www.w3.org/1998/Math/MathML\"><semantics><mrow><mi>i</mi></mrow><annotation encoding=\"application/x-tex\">i</annotation></semantics></math></span><span class=\"katex-html\" aria-hidden=\"true\"><span class=\"base\"><span class=\"strut\" style=\"height:0.6595em;\"></span><span class=\"mord mathnormal\">i</span></span></span></span>","key":"XmMqUK6CWZ"},{"type":"text","value":"の過去の応答をもとに","position":{"start":{"line":3,"column":1},"end":{"line":3,"column":1}},"key":"HwBhsMdJAS"},{"type":"inlineMath","value":"\\hat{y}_{ij}","position":{"start":{"line":3,"column":1},"end":{"line":3,"column":1}},"html":"<span class=\"katex\"><span class=\"katex-mathml\"><math xmlns=\"http://www.w3.org/1998/Math/MathML\"><semantics><mrow><msub><mover accent=\"true\"><mi>y</mi><mo>^</mo></mover><mrow><mi>i</mi><mi>j</mi></mrow></msub></mrow><annotation encoding=\"application/x-tex\">\\hat{y}_{ij}</annotation></semantics></math></span><span class=\"katex-html\" aria-hidden=\"true\"><span class=\"base\"><span class=\"strut\" style=\"height:0.9805em;vertical-align:-0.2861em;\"></span><span class=\"mord\"><span class=\"mord accent\"><span class=\"vlist-t vlist-t2\"><span class=\"vlist-r\"><span class=\"vlist\" style=\"height:0.6944em;\"><span style=\"top:-3em;\"><span class=\"pstrut\" style=\"height:3em;\"></span><span class=\"mord mathnormal\" style=\"margin-right:0.03588em;\">y</span></span><span style=\"top:-3em;\"><span class=\"pstrut\" style=\"height:3em;\"></span><span class=\"accent-body\" style=\"left:-0.1944em;\"><span class=\"mord\">^</span></span></span></span><span class=\"vlist-s\">​</span></span><span class=\"vlist-r\"><span class=\"vlist\" style=\"height:0.1944em;\"><span></span></span></span></span></span><span class=\"msupsub\"><span class=\"vlist-t vlist-t2\"><span class=\"vlist-r\"><span class=\"vlist\" style=\"height:0.3117em;\"><span style=\"top:-2.55em;margin-left:-0.0359em;margin-right:0.05em;\"><span class=\"pstrut\" style=\"height:2.7em;\"></span><span class=\"sizing reset-size6 size3 mtight\"><span class=\"mord mtight\"><span class=\"mord mathnormal mtight\" style=\"margin-right:0.05724em;\">ij</span></span></span></span></span><span class=\"vlist-s\">​</span></span><span class=\"vlist-r\"><span class=\"vlist\" style=\"height:0.2861em;\"><span></span></span></span></span></span></span></span></span></span>","key":"I3mvowF0HD"},{"type":"text","value":"を推定する","position":{"start":{"line":3,"column":1},"end":{"line":3,"column":1}},"key":"xqpHfO5ICs"}],"key":"KzL4wkVSnE"}],"key":"FR9X0oM1sk"},{"type":"block","kind":"notebook-content","children":[],"key":"g2Osj9vhRn"},{"type":"block","kind":"notebook-content","children":[{"type":"heading","depth":2,"position":{"start":{"line":1,"column":1},"end":{"line":1,"column":1}},"children":[{"type":"text","value":"モデルベース法","position":{"start":{"line":1,"column":1},"end":{"line":1,"column":1}},"key":"EMu8EvW9cs"}],"identifier":"id","label":"モデルベース法","html_id":"id-3","implicit":true,"key":"WK7cl4OGUL"},{"type":"paragraph","position":{"start":{"line":3,"column":1},"end":{"line":3,"column":1}},"children":[{"type":"text","value":"観測データの規則性を学習したモデルを事前に用意しておく方法を ","position":{"start":{"line":3,"column":1},"end":{"line":3,"column":1}},"key":"xbjjA1qIic"},{"type":"strong","position":{"start":{"line":3,"column":1},"end":{"line":3,"column":1}},"children":[{"type":"text","value":"モデルベース法（model-based method）","position":{"start":{"line":3,"column":1},"end":{"line":3,"column":1}},"key":"aJbSL6bKe9"}],"key":"Wylhk48TdO"},{"type":"text","value":" という。","position":{"start":{"line":3,"column":1},"end":{"line":3,"column":1}},"key":"bAvNTutaYt"}],"key":"vM6I81rbyX"},{"type":"paragraph","position":{"start":{"line":5,"column":1},"end":{"line":5,"column":1}},"children":[{"type":"text","value":"モデルには","position":{"start":{"line":5,"column":1},"end":{"line":5,"column":1}},"key":"QF93avaBg2"}],"key":"FIS3bqp8kd"},{"type":"list","ordered":false,"spread":false,"position":{"start":{"line":7,"column":1},"end":{"line":13,"column":1}},"children":[{"type":"listItem","spread":true,"position":{"start":{"line":7,"column":1},"end":{"line":7,"column":1}},"children":[{"type":"paragraph","children":[{"type":"text","value":"クラスタリング","position":{"start":{"line":7,"column":1},"end":{"line":7,"column":1}},"key":"Xc6jEIESlQ"}],"key":"mICc0i2KEy"}],"key":"i2CeRwd4B0"},{"type":"listItem","spread":true,"position":{"start":{"line":8,"column":1},"end":{"line":8,"column":1}},"children":[{"type":"paragraph","children":[{"type":"text","value":"回帰・分類・ランキング問題として評価値を予測するモデル","position":{"start":{"line":8,"column":1},"end":{"line":8,"column":1}},"key":"FUqAO03BZy"}],"key":"zd8Cq1hAZM"}],"key":"CayF0wgmEI"},{"type":"listItem","spread":true,"position":{"start":{"line":9,"column":1},"end":{"line":10,"column":1}},"children":[{"type":"paragraph","children":[{"type":"text","value":"トピックモデル","position":{"start":{"line":9,"column":1},"end":{"line":9,"column":1}},"key":"zevGoSow3L"}],"key":"IZ1AChuEi6"},{"type":"list","ordered":false,"spread":false,"position":{"start":{"line":10,"column":1},"end":{"line":10,"column":1}},"children":[{"type":"listItem","spread":true,"position":{"start":{"line":10,"column":1},"end":{"line":10,"column":1}},"children":[{"type":"paragraph","children":[{"type":"text","value":"LDA（Latent Dirichlet Allocation）などで評価値行列を次元削減し、嗜好を表現する情報を獲得する","position":{"start":{"line":10,"column":1},"end":{"line":10,"column":1}},"key":"TdIsDT0MAP"}],"key":"EuInDoHi5v"}],"key":"p69y8mJskd"}],"key":"A6S9MsGH2L"}],"key":"xJHabS4zel"},{"type":"listItem","spread":true,"position":{"start":{"line":11,"column":1},"end":{"line":13,"column":1}},"children":[{"type":"paragraph","children":[{"type":"text","value":"行列分解（Matrix Factorization）","position":{"start":{"line":11,"column":1},"end":{"line":11,"column":1}},"key":"KjTfVdmMTC"}],"key":"DWydPs2Y1x"},{"type":"list","ordered":false,"spread":false,"position":{"start":{"line":12,"column":1},"end":{"line":13,"column":1}},"children":[{"type":"listItem","spread":true,"position":{"start":{"line":12,"column":1},"end":{"line":13,"column":1}},"children":[{"type":"paragraph","children":[{"type":"text","value":"評価値行列をユーザー行列とアイテム行列に分解し、ユーザーベクトルとアイテムベクトルの類似度で予測評価値を計算する","position":{"start":{"line":12,"column":1},"end":{"line":12,"column":1}},"key":"Xf72nrnHnW"}],"key":"Ix1nJkdJHt"}],"key":"BTas9RpQtX"}],"key":"hfljxOIG4w"}],"key":"Lu5ApiPxSi"}],"key":"WH8DOThh59"},{"type":"paragraph","position":{"start":{"line":14,"column":1},"end":{"line":14,"column":1}},"children":[{"type":"text","value":"など様々なモデルが使われる。","position":{"start":{"line":14,"column":1},"end":{"line":14,"column":1}},"key":"gcY0Thncb6"}],"key":"YaHsFQK7RX"}],"key":"z7QHoEN6F7"},{"type":"block","kind":"notebook-content","children":[{"type":"heading","depth":2,"position":{"start":{"line":1,"column":1},"end":{"line":1,"column":1}},"children":[{"type":"text","value":"データ数","position":{"start":{"line":1,"column":1},"end":{"line":1,"column":1}},"key":"vXRKdaK6Y7"}],"identifier":"id","label":"データ数","html_id":"id-4","implicit":true,"key":"qkMti4372P"},{"type":"paragraph","position":{"start":{"line":3,"column":1},"end":{"line":3,"column":1}},"children":[{"type":"link","url":"https://www.ieice.org/publications/conference-FIT-DVDs/FIT2008/pdf/F/F_028.pdf","position":{"start":{"line":3,"column":1},"end":{"line":3,"column":1}},"children":[{"type":"text","value":"田村幸之介, & 松原仁. (2008). 協調フィルタリングにおけるデータの必要数の分析 (Doctoral dissertation, Future University Hakodate).","position":{"start":{"line":3,"column":1},"end":{"line":3,"column":1}},"key":"pPRv7IseLo"}],"urlSource":"https://www.ieice.org/publications/conference-FIT-DVDs/FIT2008/pdf/F/F_028.pdf","key":"muYDdTdKah"}],"key":"kHsZd8t4Bg"},{"type":"list","ordered":false,"spread":false,"position":{"start":{"line":5,"column":1},"end":{"line":6,"column":1}},"children":[{"type":"listItem","spread":true,"position":{"start":{"line":5,"column":1},"end":{"line":5,"column":1}},"children":[{"type":"paragraph","children":[{"type":"text","value":"ユーザーベースの手法であるGroupLensを使った。","position":{"start":{"line":5,"column":1},"end":{"line":5,"column":1}},"key":"H2IpUJ38kV"}],"key":"QItbj2F3jI"}],"key":"hjKWBMApl9"},{"type":"listItem","spread":true,"position":{"start":{"line":6,"column":1},"end":{"line":6,"column":1}},"children":[{"type":"paragraph","children":[{"type":"text","value":"データ数を減らしながら精度の変化を見たところ、最低でも8万レコードほしいという結果に","position":{"start":{"line":6,"column":1},"end":{"line":6,"column":1}},"key":"bEyYf0Gi6O"}],"key":"BTBzckdVzr"}],"key":"ls7hLT8eLX"}],"key":"Jo1tR1oo0z"}],"key":"ATnKPv5bl0"},{"type":"block","kind":"notebook-content","children":[{"type":"heading","depth":2,"position":{"start":{"line":1,"column":1},"end":{"line":1,"column":1}},"children":[{"type":"text","value":"参考","position":{"start":{"line":1,"column":1},"end":{"line":1,"column":1}},"key":"aueLWhWP0f"}],"identifier":"id","label":"参考","html_id":"id-5","implicit":true,"key":"PjQRhYWrCC"},{"type":"list","ordered":false,"spread":false,"position":{"start":{"line":3,"column":1},"end":{"line":3,"column":1}},"children":[{"type":"listItem","spread":true,"position":{"start":{"line":3,"column":1},"end":{"line":3,"column":1}},"children":[{"type":"paragraph","children":[{"type":"link","url":"https://zenn.dev/datasciencekun/articles/33d3be4c4ce4ea","position":{"start":{"line":3,"column":1},"end":{"line":3,"column":1}},"children":[{"type":"text","value":"レコメンドシステム——協調フィルタリング(Collaborative Filtering)","position":{"start":{"line":3,"column":1},"end":{"line":3,"column":1}},"key":"yPCCULaYr4"}],"urlSource":"https://zenn.dev/datasciencekun/articles/33d3be4c4ce4ea","key":"u5EpOZFZJz"}],"key":"IcDBTxuwvY"}],"key":"U2iLItK8hR"}],"key":"S1r6167Kdh"}],"key":"kpaW3iEixg"}],"key":"TI5lLeiBOW"},"references":{"cite":{"order":[],"data":{}}},"footer":{"navigation":{"prev":{"title":"内容ベースフィルタリング","url":"/recommender-system/content-based-filtering","group":"推薦システム"},"next":{"title":"行列分解に基づく推薦システム","url":"/recommender-system/matrix-factorization","group":"推薦システム"}}},"domain":"http://localhost:3000"}