{"version":3,"kind":"Notebook","sha256":"7ead5e0b73875c68d3f429f7740c31d3fa054166cc73501d91a8ae8911f82aa0","slug":"software-engineering.algorithms.bit","location":"/software_engineering/algorithms/bit.ipynb","dependencies":[],"frontmatter":{"title":"bit演算","content_includes_title":false,"kernelspec":{"name":"python3","display_name":"notes (3.10.18)","language":"python"},"authors":[{"nameParsed":{"literal":"mitama","family":"mitama"},"name":"mitama","id":"contributors-myst-generated-uid-0"}],"github":"https://github.com/nigimitama/notes","copyright":"© mitama","numbering":{"title":{"offset":2}},"source_url":"https://github.com/nigimitama/notes/blob/main/book/software_engineering/algorithms/bit.ipynb","edit_url":"https://github.com/nigimitama/notes/edit/main/book/software_engineering/algorithms/bit.ipynb","exports":[{"format":"ipynb","filename":"bit.ipynb","url":"/notes/build/bit-4f9e0efaf1c9dc907c5c3d66e4067d36.ipynb"}]},"widgets":{},"mdast":{"type":"root","children":[{"type":"block","kind":"notebook-content","children":[{"type":"paragraph","position":{"start":{"line":1,"column":1},"end":{"line":1,"column":1}},"children":[{"type":"text","value":"ビット演算は整数をビット列として扱い、各ビットに対して論理演算やシフト演算を行う。高速・省メモリなため、競技プログラミングや低レベルプログラミングで頻繁に使われる。","position":{"start":{"line":1,"column":1},"end":{"line":1,"column":1}},"key":"jAVZ8BUR5Z"}],"key":"oLaFK8Bcfj"},{"type":"table","position":{"start":{"line":3,"column":1},"end":{"line":10,"column":1}},"children":[{"type":"tableRow","position":{"start":{"line":3,"column":1},"end":{"line":3,"column":1}},"children":[{"type":"tableCell","header":true,"position":{"start":{"line":3,"column":1},"end":{"line":3,"column":1}},"children":[{"type":"text","value":"演算子","position":{"start":{"line":3,"column":1},"end":{"line":3,"column":1}},"key":"sebEkDFmFL"}],"key":"PvnWNJYARy"},{"type":"tableCell","header":true,"position":{"start":{"line":3,"column":1},"end":{"line":3,"column":1}},"children":[{"type":"text","value":"名前","position":{"start":{"line":3,"column":1},"end":{"line":3,"column":1}},"key":"KnndECDgwt"}],"key":"a8CQXpoCn2"},{"type":"tableCell","header":true,"position":{"start":{"line":3,"column":1},"end":{"line":3,"column":1}},"children":[{"type":"text","value":"例 (","position":{"start":{"line":3,"column":1},"end":{"line":3,"column":1}},"key":"HtUpbMtkuZ"},{"type":"inlineCode","value":"a=0b1010","position":{"start":{"line":3,"column":1},"end":{"line":3,"column":1}},"key":"nJ85DvURek"},{"type":"text","value":", ","position":{"start":{"line":3,"column":1},"end":{"line":3,"column":1}},"key":"iva7Ttk7KB"},{"type":"inlineCode","value":"b=0b1100","position":{"start":{"line":3,"column":1},"end":{"line":3,"column":1}},"key":"ICAJBvE7u3"},{"type":"text","value":")","position":{"start":{"line":3,"column":1},"end":{"line":3,"column":1}},"key":"I1v2pMVS1B"}],"key":"hzhl7QUlqq"},{"type":"tableCell","header":true,"position":{"start":{"line":3,"column":1},"end":{"line":3,"column":1}},"children":[{"type":"text","value":"結果","position":{"start":{"line":3,"column":1},"end":{"line":3,"column":1}},"key":"NZU3aRUu6q"}],"key":"Em065BI4Sg"}],"key":"IeOi3AF51H"},{"type":"tableRow","position":{"start":{"line":5,"column":1},"end":{"line":5,"column":1}},"children":[{"type":"tableCell","position":{"start":{"line":5,"column":1},"end":{"line":5,"column":1}},"children":[{"type":"inlineCode","value":"&","position":{"start":{"line":5,"column":1},"end":{"line":5,"column":1}},"key":"pCQtDexGYi"}],"key":"dOgiBEswAl"},{"type":"tableCell","position":{"start":{"line":5,"column":1},"end":{"line":5,"column":1}},"children":[{"type":"text","value":"AND","position":{"start":{"line":5,"column":1},"end":{"line":5,"column":1}},"key":"WYHfXCXFlR"}],"key":"yU4aA95kAM"},{"type":"tableCell","position":{"start":{"line":5,"column":1},"end":{"line":5,"column":1}},"children":[{"type":"inlineCode","value":"a & b","position":{"start":{"line":5,"column":1},"end":{"line":5,"column":1}},"key":"bCMTveZhZt"}],"key":"zv2RwgNPM5"},{"type":"tableCell","position":{"start":{"line":5,"column":1},"end":{"line":5,"column":1}},"children":[{"type":"inlineCode","value":"0b1000","position":{"start":{"line":5,"column":1},"end":{"line":5,"column":1}},"key":"HzaNR92ER5"}],"key":"Shfhkpcd3J"}],"key":"lnb5FkLMcD"},{"type":"tableRow","position":{"start":{"line":6,"column":1},"end":{"line":6,"column":1}},"children":[{"type":"tableCell","position":{"start":{"line":6,"column":1},"end":{"line":6,"column":1}},"children":[{"type":"inlineCode","value":"|","position":{"start":{"line":6,"column":1},"end":{"line":6,"column":1}},"key":"bLKOdoZYfT"}],"key":"nXVkJ9RIVI"},{"type":"tableCell","position":{"start":{"line":6,"column":1},"end":{"line":6,"column":1}},"children":[{"type":"text","value":"OR","position":{"start":{"line":6,"column":1},"end":{"line":6,"column":1}},"key":"qtvEQv9qt4"}],"key":"FiWNZdJoXX"},{"type":"tableCell","position":{"start":{"line":6,"column":1},"end":{"line":6,"column":1}},"children":[{"type":"inlineCode","value":"a | b","position":{"start":{"line":6,"column":1},"end":{"line":6,"column":1}},"key":"zv3zdnpFwi"}],"key":"mRdPHJldpC"},{"type":"tableCell","position":{"start":{"line":6,"column":1},"end":{"line":6,"column":1}},"children":[{"type":"inlineCode","value":"0b1110","position":{"start":{"line":6,"column":1},"end":{"line":6,"column":1}},"key":"B5XmCK9Q9T"}],"key":"eFnXVoFyhW"}],"key":"s2JancSPBV"},{"type":"tableRow","position":{"start":{"line":7,"column":1},"end":{"line":7,"column":1}},"children":[{"type":"tableCell","position":{"start":{"line":7,"column":1},"end":{"line":7,"column":1}},"children":[{"type":"inlineCode","value":"^","position":{"start":{"line":7,"column":1},"end":{"line":7,"column":1}},"key":"B1EV41apiR"}],"key":"rwYnYAzQ8S"},{"type":"tableCell","position":{"start":{"line":7,"column":1},"end":{"line":7,"column":1}},"children":[{"type":"text","value":"XOR","position":{"start":{"line":7,"column":1},"end":{"line":7,"column":1}},"key":"XFOVcoCHLN"}],"key":"QX3mnrlQp2"},{"type":"tableCell","position":{"start":{"line":7,"column":1},"end":{"line":7,"column":1}},"children":[{"type":"inlineCode","value":"a ^ b","position":{"start":{"line":7,"column":1},"end":{"line":7,"column":1}},"key":"otsMFpYfSg"}],"key":"ZMN901wWZ1"},{"type":"tableCell","position":{"start":{"line":7,"column":1},"end":{"line":7,"column":1}},"children":[{"type":"inlineCode","value":"0b0110","position":{"start":{"line":7,"column":1},"end":{"line":7,"column":1}},"key":"AcePVtyeUW"}],"key":"PLY5OcmL6d"}],"key":"s0PiO1Fmqo"},{"type":"tableRow","position":{"start":{"line":8,"column":1},"end":{"line":8,"column":1}},"children":[{"type":"tableCell","position":{"start":{"line":8,"column":1},"end":{"line":8,"column":1}},"children":[{"type":"inlineCode","value":"~","position":{"start":{"line":8,"column":1},"end":{"line":8,"column":1}},"key":"aFD5KqWfhb"}],"key":"yKZuFyMYSv"},{"type":"tableCell","position":{"start":{"line":8,"column":1},"end":{"line":8,"column":1}},"children":[{"type":"text","value":"NOT","position":{"start":{"line":8,"column":1},"end":{"line":8,"column":1}},"key":"t8JtGtFPUT"}],"key":"F4ZDpFPwIC"},{"type":"tableCell","position":{"start":{"line":8,"column":1},"end":{"line":8,"column":1}},"children":[{"type":"inlineCode","value":"~a","position":{"start":{"line":8,"column":1},"end":{"line":8,"column":1}},"key":"UmrJcPsx7z"}],"key":"lbqKFjBnEK"},{"type":"tableCell","position":{"start":{"line":8,"column":1},"end":{"line":8,"column":1}},"children":[{"type":"inlineCode","value":"-11","position":{"start":{"line":8,"column":1},"end":{"line":8,"column":1}},"key":"j77PRzQEkN"},{"type":"text","value":"（2の補数）","position":{"start":{"line":8,"column":1},"end":{"line":8,"column":1}},"key":"IOmafcLYHE"}],"key":"z6e08frrrz"}],"key":"Rk7yKG8egO"},{"type":"tableRow","position":{"start":{"line":9,"column":1},"end":{"line":9,"column":1}},"children":[{"type":"tableCell","position":{"start":{"line":9,"column":1},"end":{"line":9,"column":1}},"children":[{"type":"inlineCode","value":"<<","position":{"start":{"line":9,"column":1},"end":{"line":9,"column":1}},"key":"Aae1ZjWgqc"}],"key":"tZLH9YXAZ7"},{"type":"tableCell","position":{"start":{"line":9,"column":1},"end":{"line":9,"column":1}},"children":[{"type":"text","value":"左シフト","position":{"start":{"line":9,"column":1},"end":{"line":9,"column":1}},"key":"nPuUoD1t8b"}],"key":"LUsBSoAzyE"},{"type":"tableCell","position":{"start":{"line":9,"column":1},"end":{"line":9,"column":1}},"children":[{"type":"inlineCode","value":"a << 1","position":{"start":{"line":9,"column":1},"end":{"line":9,"column":1}},"key":"HiqPLCEwHf"}],"key":"YDJ2kwR42J"},{"type":"tableCell","position":{"start":{"line":9,"column":1},"end":{"line":9,"column":1}},"children":[{"type":"inlineCode","value":"0b10100","position":{"start":{"line":9,"column":1},"end":{"line":9,"column":1}},"key":"kHmOZpIYds"}],"key":"XYFNuYke5Z"}],"key":"Av7E7I3x5D"},{"type":"tableRow","position":{"start":{"line":10,"column":1},"end":{"line":10,"column":1}},"children":[{"type":"tableCell","position":{"start":{"line":10,"column":1},"end":{"line":10,"column":1}},"children":[{"type":"inlineCode","value":">>","position":{"start":{"line":10,"column":1},"end":{"line":10,"column":1}},"key":"JhuZPbc319"}],"key":"ooACJhL8cT"},{"type":"tableCell","position":{"start":{"line":10,"column":1},"end":{"line":10,"column":1}},"children":[{"type":"text","value":"右シフト","position":{"start":{"line":10,"column":1},"end":{"line":10,"column":1}},"key":"t66xkVLpzN"}],"key":"at9uXYS92E"},{"type":"tableCell","position":{"start":{"line":10,"column":1},"end":{"line":10,"column":1}},"children":[{"type":"inlineCode","value":"a >> 1","position":{"start":{"line":10,"column":1},"end":{"line":10,"column":1}},"key":"Pcz7c531Hc"}],"key":"Ta0aKd3L7T"},{"type":"tableCell","position":{"start":{"line":10,"column":1},"end":{"line":10,"column":1}},"children":[{"type":"inlineCode","value":"0b0101","position":{"start":{"line":10,"column":1},"end":{"line":10,"column":1}},"key":"xjwtaCkA6Z"}],"key":"IYQOfGHYAN"}],"key":"bCQvr2r0hR"}],"key":"VE0AqDKBiS"}],"key":"vB6RwN0Kpf"},{"type":"block","kind":"notebook-code","children":[{"type":"code","lang":"python","executable":true,"value":"a = 0b1010  # 10\nb = 0b1100  # 12\n\nprint(f\"a     = {a:04b} ({a})\")\nprint(f\"b     = {b:04b} ({b})\")\nprint(f\"a & b = {a & b:04b} ({a & b})\")   # AND\nprint(f\"a | b = {a | b:04b} ({a | b})\")   # OR\nprint(f\"a ^ b = {a ^ b:04b} ({a ^ b})\")   # XOR\nprint(f\"a << 1= {a << 1:05b} ({a << 1})\") # 左シフト（×2）\nprint(f\"a >> 1= {a >> 1:04b} ({a >> 1})\") # 右シフト（÷2）","key":"HeQXBbpvQc"},{"type":"outputs","id":"vojlSF74C4mdUcmfgHGde","children":[{"type":"output","jupyter_data":{"name":"stdout","output_type":"stream","text":"a     = 1010 (10)\nb     = 1100 (12)\na & b = 1000 (8)\na | b = 1110 (14)\na ^ b = 0110 (6)\na << 1= 10100 (20)\na >> 1= 0101 (5)\n"},"children":[],"key":"np3O9vQ0hW"}],"key":"P9VSDCdxQ3"}],"key":"VSFbgfOPHX"},{"type":"block","kind":"notebook-content","children":[{"type":"heading","depth":2,"position":{"start":{"line":1,"column":1},"end":{"line":1,"column":1}},"children":[{"type":"text","value":"ビットマスク","position":{"start":{"line":1,"column":1},"end":{"line":1,"column":1}},"key":"tiGEMgjn6t"}],"identifier":"id","label":"ビットマスク","html_id":"id","implicit":true,"key":"nCHRbTt4vV"},{"type":"paragraph","position":{"start":{"line":3,"column":1},"end":{"line":3,"column":1}},"children":[{"type":"inlineCode","value":"1 << k","position":{"start":{"line":3,"column":1},"end":{"line":3,"column":1}},"key":"KqYR5qjBq5"},{"type":"text","value":" で k ビット目だけが立ったマスクを作り、特定ビットの操作を行う。","position":{"start":{"line":3,"column":1},"end":{"line":3,"column":1}},"key":"ZS4RyQZxet"}],"key":"x33BVslwqx"},{"type":"table","position":{"start":{"line":5,"column":1},"end":{"line":10,"column":1}},"children":[{"type":"tableRow","position":{"start":{"line":5,"column":1},"end":{"line":5,"column":1}},"children":[{"type":"tableCell","header":true,"position":{"start":{"line":5,"column":1},"end":{"line":5,"column":1}},"children":[{"type":"text","value":"操作","position":{"start":{"line":5,"column":1},"end":{"line":5,"column":1}},"key":"QGQyXDWB0M"}],"key":"pGvVnO0p4T"},{"type":"tableCell","header":true,"position":{"start":{"line":5,"column":1},"end":{"line":5,"column":1}},"children":[{"type":"text","value":"コード","position":{"start":{"line":5,"column":1},"end":{"line":5,"column":1}},"key":"zXxCLzTuKP"}],"key":"Ef6Z2UOv11"}],"key":"vDRa3hqVTb"},{"type":"tableRow","position":{"start":{"line":7,"column":1},"end":{"line":7,"column":1}},"children":[{"type":"tableCell","position":{"start":{"line":7,"column":1},"end":{"line":7,"column":1}},"children":[{"type":"text","value":"k ビット目を立てる（set）","position":{"start":{"line":7,"column":1},"end":{"line":7,"column":1}},"key":"nhz9YnF8rs"}],"key":"AO4b5jWXB8"},{"type":"tableCell","position":{"start":{"line":7,"column":1},"end":{"line":7,"column":1}},"children":[{"type":"inlineCode","value":"x | (1 << k)","position":{"start":{"line":7,"column":1},"end":{"line":7,"column":1}},"key":"UjR6BElNRR"}],"key":"AE7wipht8x"}],"key":"O50KEijfaI"},{"type":"tableRow","position":{"start":{"line":8,"column":1},"end":{"line":8,"column":1}},"children":[{"type":"tableCell","position":{"start":{"line":8,"column":1},"end":{"line":8,"column":1}},"children":[{"type":"text","value":"k ビット目を消す（clear）","position":{"start":{"line":8,"column":1},"end":{"line":8,"column":1}},"key":"tmQbY6NXCl"}],"key":"K5yYY3s2Lx"},{"type":"tableCell","position":{"start":{"line":8,"column":1},"end":{"line":8,"column":1}},"children":[{"type":"inlineCode","value":"x & ~(1 << k)","position":{"start":{"line":8,"column":1},"end":{"line":8,"column":1}},"key":"i3YZ5WUleV"}],"key":"ZTDWZdZyHD"}],"key":"px8KS1w3he"},{"type":"tableRow","position":{"start":{"line":9,"column":1},"end":{"line":9,"column":1}},"children":[{"type":"tableCell","position":{"start":{"line":9,"column":1},"end":{"line":9,"column":1}},"children":[{"type":"text","value":"k ビット目を反転（toggle）","position":{"start":{"line":9,"column":1},"end":{"line":9,"column":1}},"key":"d1pyZjECMw"}],"key":"cOTiLwJe20"},{"type":"tableCell","position":{"start":{"line":9,"column":1},"end":{"line":9,"column":1}},"children":[{"type":"inlineCode","value":"x ^ (1 << k)","position":{"start":{"line":9,"column":1},"end":{"line":9,"column":1}},"key":"E0tqniQpnc"}],"key":"VV5hPMIu4E"}],"key":"XKhvglUAs4"},{"type":"tableRow","position":{"start":{"line":10,"column":1},"end":{"line":10,"column":1}},"children":[{"type":"tableCell","position":{"start":{"line":10,"column":1},"end":{"line":10,"column":1}},"children":[{"type":"text","value":"k ビット目を取得（get）","position":{"start":{"line":10,"column":1},"end":{"line":10,"column":1}},"key":"ZraHWFXfYl"}],"key":"eh0SOggVbx"},{"type":"tableCell","position":{"start":{"line":10,"column":1},"end":{"line":10,"column":1}},"children":[{"type":"inlineCode","value":"(x >> k) & 1","position":{"start":{"line":10,"column":1},"end":{"line":10,"column":1}},"key":"RRrOarXz4b"}],"key":"YTA574VVsg"}],"key":"wP6zVUZXaH"}],"key":"tV0bJ23S5O"}],"key":"FiOlnDyKKL"},{"type":"block","kind":"notebook-code","children":[{"type":"code","lang":"python","executable":true,"value":"x = 0b0101  # 5\n\ndef show(label, val, width=4):\n    print(f\"{label:30s} = {val:0{width}b} ({val})\")\n\nshow(\"x\", x)\nshow(\"set bit 1   : x | (1<<1)\", x | (1 << 1))\nshow(\"clear bit 2 : x & ~(1<<2)\", x & ~(1 << 2))\nshow(\"toggle bit 0: x ^ (1<<0)\", x ^ (1 << 0))\nprint(f\"{'get bit 2   : (x>>2)&1':30s} = {(x >> 2) & 1}\")","key":"CcvfPD8caA"},{"type":"outputs","id":"EGvPbAP5ym7Fx7ZeYlSKL","children":[{"type":"output","jupyter_data":{"name":"stdout","output_type":"stream","text":"x                              = 0101 (5)\nset bit 1   : x | (1<<1)       = 0111 (7)\nclear bit 2 : x & ~(1<<2)      = 0001 (1)\ntoggle bit 0: x ^ (1<<0)       = 0100 (4)\nget bit 2   : (x>>2)&1         = 1\n"},"children":[],"key":"gMyS3FcCPw"}],"key":"Ig1SupYH5p"}],"key":"wAj55JX9bo"},{"type":"block","kind":"notebook-content","children":[{"type":"heading","depth":2,"position":{"start":{"line":1,"column":1},"end":{"line":1,"column":1}},"children":[{"type":"text","value":"よく使うイディオム","position":{"start":{"line":1,"column":1},"end":{"line":1,"column":1}},"key":"aXwNu8vSru"}],"identifier":"id","label":"よく使うイディオム","html_id":"id-1","implicit":true,"key":"qugr3ZWpi4"},{"type":"heading","depth":3,"position":{"start":{"line":3,"column":1},"end":{"line":3,"column":1}},"children":[{"type":"text","value":"2の累乗判定","position":{"start":{"line":3,"column":1},"end":{"line":3,"column":1}},"key":"AKdyjHslk1"}],"identifier":"id-2","label":"2の累乗判定","html_id":"id-2","implicit":true,"key":"UXZRMNBLbm"},{"type":"paragraph","position":{"start":{"line":5,"column":1},"end":{"line":5,"column":1}},"children":[{"type":"inlineCode","value":"n & (n - 1) == 0","position":{"start":{"line":5,"column":1},"end":{"line":5,"column":1}},"key":"xW5sAWNgmb"},{"type":"text","value":" が成り立つとき n は 2 の累乗（n > 0 を前提）。","position":{"start":{"line":5,"column":1},"end":{"line":5,"column":1}},"key":"CqZjra8WZe"}],"key":"CLQPj32217"},{"type":"paragraph","position":{"start":{"line":7,"column":1},"end":{"line":7,"column":1}},"children":[{"type":"strong","position":{"start":{"line":7,"column":1},"end":{"line":7,"column":1}},"children":[{"type":"text","value":"なぜ？","position":{"start":{"line":7,"column":1},"end":{"line":7,"column":1}},"key":"n5mFmhnDKN"}],"key":"PqVaXQ1HfJ"},{"type":"text","value":" 2の累乗は ","position":{"start":{"line":7,"column":1},"end":{"line":7,"column":1}},"key":"O0yr4tmtNP"},{"type":"inlineCode","value":"100...0","position":{"start":{"line":7,"column":1},"end":{"line":7,"column":1}},"key":"dbA0NW49Vt"},{"type":"text","value":" の形。","position":{"start":{"line":7,"column":1},"end":{"line":7,"column":1}},"key":"petZByK2kF"},{"type":"inlineCode","value":"n - 1","position":{"start":{"line":7,"column":1},"end":{"line":7,"column":1}},"key":"blQjNmkgMh"},{"type":"text","value":" は ","position":{"start":{"line":7,"column":1},"end":{"line":7,"column":1}},"key":"Y5rEdj3CJU"},{"type":"inlineCode","value":"011...1","position":{"start":{"line":7,"column":1},"end":{"line":7,"column":1}},"key":"mn9HjT1qWR"},{"type":"text","value":" になるので AND が 0 になる。","position":{"start":{"line":7,"column":1},"end":{"line":7,"column":1}},"key":"DI2PEUrCfp"}],"key":"uWyYgdXpio"},{"type":"heading","depth":3,"position":{"start":{"line":9,"column":1},"end":{"line":9,"column":1}},"children":[{"type":"text","value":"最下位ビットの取り出し（LSB）","position":{"start":{"line":9,"column":1},"end":{"line":9,"column":1}},"key":"KhcvwxfaZX"}],"identifier":"id-lsb","label":"最下位ビットの取り出し（LSB）","html_id":"id-lsb","implicit":true,"key":"FZIZdR9GUk"},{"type":"paragraph","position":{"start":{"line":11,"column":1},"end":{"line":11,"column":1}},"children":[{"type":"inlineCode","value":"n & (-n)","position":{"start":{"line":11,"column":1},"end":{"line":11,"column":1}},"key":"iuxbaE2EMt"},{"type":"text","value":" で最下位の立っているビットだけを取り出せる。Fenwick Tree（BIT）の根幹。","position":{"start":{"line":11,"column":1},"end":{"line":11,"column":1}},"key":"Pu53R61u27"}],"key":"qGRsyjbRFI"},{"type":"heading","depth":3,"position":{"start":{"line":13,"column":1},"end":{"line":13,"column":1}},"children":[{"type":"text","value":"立っているビット数（ポップカウント）","position":{"start":{"line":13,"column":1},"end":{"line":13,"column":1}},"key":"Pnz8hVekSq"}],"identifier":"id","label":"立っているビット数（ポップカウント）","html_id":"id-3","implicit":true,"key":"zjA2ViY9zw"},{"type":"paragraph","position":{"start":{"line":15,"column":1},"end":{"line":15,"column":1}},"children":[{"type":"inlineCode","value":"bin(n).count('1')","position":{"start":{"line":15,"column":1},"end":{"line":15,"column":1}},"key":"HxobiIgNep"},{"type":"text","value":" または ","position":{"start":{"line":15,"column":1},"end":{"line":15,"column":1}},"key":"xxcvtp8fwL"},{"type":"inlineCode","value":"n.bit_count()","position":{"start":{"line":15,"column":1},"end":{"line":15,"column":1}},"key":"Fcm4X4RaNX"},{"type":"text","value":"（Python 3.10+）。","position":{"start":{"line":15,"column":1},"end":{"line":15,"column":1}},"key":"eY4wSZj4wQ"}],"key":"P84PCH2v9c"}],"key":"OfWQXxsIq6"},{"type":"block","kind":"notebook-code","children":[{"type":"code","lang":"python","executable":true,"value":"def is_power_of_2(n: int) -> bool:\n    return n > 0 and (n & (n - 1)) == 0\n\ndef lsb(n: int) -> int:\n    \"\"\"最下位の立っているビットを取り出す\"\"\"\n    return n & (-n)\n\ndef popcount(n: int) -> int:\n    return bin(n).count('1')\n\n# 2の累乗判定\nfor n in [0, 1, 2, 3, 4, 6, 8, 16]:\n    print(f\"is_power_of_2({n:2d}) = {is_power_of_2(n)}\")\n\nprint()\n\n# LSB\nn = 0b10110  # 22\nprint(f\"n   = {n:05b} ({n})\")\nprint(f\"LSB = {lsb(n):05b} ({lsb(n)})\")\n\nprint()\n\n# ポップカウント\nfor n in [0b0000, 0b1010, 0b1111, 255]:\n    print(f\"popcount({n:08b}) = {popcount(n)}\")","key":"icUEaNUf52"},{"type":"outputs","id":"OKomWxdySXrSOoOoTNcWE","children":[{"type":"output","jupyter_data":{"name":"stdout","output_type":"stream","text":"is_power_of_2( 0) = False\nis_power_of_2( 1) = True\nis_power_of_2( 2) = True\nis_power_of_2( 3) = False\nis_power_of_2( 4) = True\nis_power_of_2( 6) = False\nis_power_of_2( 8) = True\nis_power_of_2(16) = True\n\nn   = 10110 (22)\nLSB = 00010 (2)\n\npopcount(00000000) = 0\npopcount(00001010) = 2\npopcount(00001111) = 4\npopcount(11111111) = 8\n"},"children":[],"key":"taw28ggUhV"}],"key":"BIx5OKgMue"}],"key":"rohYv6XJPi"},{"type":"block","kind":"notebook-content","children":[{"type":"heading","depth":2,"position":{"start":{"line":1,"column":1},"end":{"line":1,"column":1}},"children":[{"type":"text","value":"応用：部分集合の列挙（ビット全探索）","position":{"start":{"line":1,"column":1},"end":{"line":1,"column":1}},"key":"QOHohhMbTq"}],"identifier":"id","label":"応用：部分集合の列挙（ビット全探索）","html_id":"id-4","implicit":true,"key":"TvjPeCdma7"},{"type":"paragraph","position":{"start":{"line":3,"column":1},"end":{"line":3,"column":1}},"children":[{"type":"text","value":"n 個の要素からなる集合の全部分集合を ","position":{"start":{"line":3,"column":1},"end":{"line":3,"column":1}},"key":"oQUn98mFTS"},{"type":"inlineCode","value":"0","position":{"start":{"line":3,"column":1},"end":{"line":3,"column":1}},"key":"CE3V0y4syX"},{"type":"text","value":" から ","position":{"start":{"line":3,"column":1},"end":{"line":3,"column":1}},"key":"UWmmlMV3cd"},{"type":"inlineCode","value":"2^n - 1","position":{"start":{"line":3,"column":1},"end":{"line":3,"column":1}},"key":"u2Ls9RemGm"},{"type":"text","value":" までのビット列で表現する。各ビットが「その要素を選ぶかどうか」に対応する。計算量は O(2^n)。","position":{"start":{"line":3,"column":1},"end":{"line":3,"column":1}},"key":"LqEddRP4Ob"}],"key":"jfXtSn6j4G"}],"key":"YmwmJ69wd0"},{"type":"block","kind":"notebook-code","children":[{"type":"code","lang":"python","executable":true,"value":"items = [\"A\", \"B\", \"C\"]\nn = len(items)\n\nprint(\"全部分集合:\")\nfor mask in range(1 << n):\n    subset = [items[i] for i in range(n) if (mask >> i) & 1]\n    print(f\"  {mask:03b} -> {subset}\")\n\nprint()\n\n# 応用例: 合計がちょうど target になる部分集合を列挙\nvalues = [1, 3, 5, 7]\ntarget = 8\nn = len(values)\n\nprint(f\"values={values}, target={target} になる部分集合:\")\nfor mask in range(1 << n):\n    subset = [values[i] for i in range(n) if (mask >> i) & 1]\n    if sum(subset) == target:\n        print(f\"  {subset}\")","key":"PYj7GDOInn"},{"type":"outputs","id":"X0oOaBgnzZ_kwOZbFXDp2","children":[{"type":"output","jupyter_data":{"name":"stdout","output_type":"stream","text":"全部分集合:\n  000 -> []\n  001 -> ['A']\n  010 -> ['B']\n  011 -> ['A', 'B']\n  100 -> ['C']\n  101 -> ['A', 'C']\n  110 -> ['B', 'C']\n  111 -> ['A', 'B', 'C']\n\nvalues=[1, 3, 5, 7], target=8 になる部分集合:\n  [3, 5]\n  [1, 7]\n"},"children":[],"key":"AZUky5V385"}],"key":"bLm38bPcF4"}],"key":"qCd8xnKGsW"},{"type":"block","kind":"notebook-content","children":[{"type":"heading","depth":2,"position":{"start":{"line":1,"column":1},"end":{"line":1,"column":1}},"children":[{"type":"text","value":"応用：ビット DP","position":{"start":{"line":1,"column":1},"end":{"line":1,"column":1}},"key":"ZkXYN3ShyO"}],"identifier":"id-dp","label":"応用：ビット DP","html_id":"id-dp","implicit":true,"key":"h0EMrkKdpJ"},{"type":"paragraph","position":{"start":{"line":3,"column":1},"end":{"line":3,"column":1}},"children":[{"type":"text","value":"状態を集合（ビット列）で表すDPをビットDPという。典型例として巡回セールスマン問題（TSP）がある。","position":{"start":{"line":3,"column":1},"end":{"line":3,"column":1}},"key":"GO9OTORLyA"}],"key":"y3XH41aZmD"},{"type":"paragraph","position":{"start":{"line":5,"column":1},"end":{"line":5,"column":1}},"children":[{"type":"inlineCode","value":"dp[S][v]","position":{"start":{"line":5,"column":1},"end":{"line":5,"column":1}},"key":"NEC5u9vCIU"},{"type":"text","value":" = 頂点集合 S を訪問済みで、現在頂点 v にいるときの最小コスト。","position":{"start":{"line":5,"column":1},"end":{"line":5,"column":1}},"key":"UkYLCor2kq"}],"key":"l2HzYXJjGB"},{"type":"math","value":"dp[S | (1 << u)][u] = \\min(dp[S | (1 << u)][u], \\; dp[S][v] + \\text{cost}[v][u])","position":{"start":{"line":7,"column":1},"end":{"line":9,"column":1}},"html":"<span class=\"katex-display\"><span class=\"katex\"><span class=\"katex-mathml\"><math xmlns=\"http://www.w3.org/1998/Math/MathML\" display=\"block\"><semantics><mrow><mi>d</mi><mi>p</mi><mo stretchy=\"false\">[</mo><mi>S</mi><mi mathvariant=\"normal\">∣</mi><mo stretchy=\"false\">(</mo><mn>1</mn><mo>&lt;</mo><mo>&lt;</mo><mi>u</mi><mo stretchy=\"false\">)</mo><mo stretchy=\"false\">]</mo><mo stretchy=\"false\">[</mo><mi>u</mi><mo stretchy=\"false\">]</mo><mo>=</mo><mi>min</mi><mo>⁡</mo><mo stretchy=\"false\">(</mo><mi>d</mi><mi>p</mi><mo stretchy=\"false\">[</mo><mi>S</mi><mi mathvariant=\"normal\">∣</mi><mo stretchy=\"false\">(</mo><mn>1</mn><mo>&lt;</mo><mo>&lt;</mo><mi>u</mi><mo stretchy=\"false\">)</mo><mo stretchy=\"false\">]</mo><mo stretchy=\"false\">[</mo><mi>u</mi><mo stretchy=\"false\">]</mo><mo separator=\"true\">,</mo><mtext>  </mtext><mi>d</mi><mi>p</mi><mo stretchy=\"false\">[</mo><mi>S</mi><mo stretchy=\"false\">]</mo><mo stretchy=\"false\">[</mo><mi>v</mi><mo stretchy=\"false\">]</mo><mo>+</mo><mtext>cost</mtext><mo stretchy=\"false\">[</mo><mi>v</mi><mo stretchy=\"false\">]</mo><mo stretchy=\"false\">[</mo><mi>u</mi><mo stretchy=\"false\">]</mo><mo stretchy=\"false\">)</mo></mrow><annotation encoding=\"application/x-tex\">dp[S | (1 &lt;&lt; u)][u] = \\min(dp[S | (1 &lt;&lt; u)][u], \\; dp[S][v] + \\text{cost}[v][u])</annotation></semantics></math></span><span class=\"katex-html\" aria-hidden=\"true\"><span class=\"base\"><span class=\"strut\" style=\"height:1em;vertical-align:-0.25em;\"></span><span class=\"mord mathnormal\">d</span><span class=\"mord mathnormal\">p</span><span class=\"mopen\">[</span><span class=\"mord mathnormal\" style=\"margin-right:0.05764em;\">S</span><span class=\"mord\">∣</span><span class=\"mopen\">(</span><span class=\"mord\">1</span><span class=\"mspace\" style=\"margin-right:0.2778em;\"></span><span class=\"mrel\">&lt;&lt;</span><span class=\"mspace\" style=\"margin-right:0.2778em;\"></span></span><span class=\"base\"><span class=\"strut\" style=\"height:1em;vertical-align:-0.25em;\"></span><span class=\"mord mathnormal\">u</span><span class=\"mclose\">)]</span><span class=\"mopen\">[</span><span class=\"mord mathnormal\">u</span><span class=\"mclose\">]</span><span class=\"mspace\" style=\"margin-right:0.2778em;\"></span><span class=\"mrel\">=</span><span class=\"mspace\" style=\"margin-right:0.2778em;\"></span></span><span class=\"base\"><span class=\"strut\" style=\"height:1em;vertical-align:-0.25em;\"></span><span class=\"mop\">min</span><span class=\"mopen\">(</span><span class=\"mord mathnormal\">d</span><span class=\"mord mathnormal\">p</span><span class=\"mopen\">[</span><span class=\"mord mathnormal\" style=\"margin-right:0.05764em;\">S</span><span class=\"mord\">∣</span><span class=\"mopen\">(</span><span class=\"mord\">1</span><span class=\"mspace\" style=\"margin-right:0.2778em;\"></span><span class=\"mrel\">&lt;&lt;</span><span class=\"mspace\" style=\"margin-right:0.2778em;\"></span></span><span class=\"base\"><span class=\"strut\" style=\"height:1em;vertical-align:-0.25em;\"></span><span class=\"mord mathnormal\">u</span><span class=\"mclose\">)]</span><span class=\"mopen\">[</span><span class=\"mord mathnormal\">u</span><span class=\"mclose\">]</span><span class=\"mpunct\">,</span><span class=\"mspace\" style=\"margin-right:0.2778em;\"></span><span class=\"mspace\" style=\"margin-right:0.1667em;\"></span><span class=\"mord mathnormal\">d</span><span class=\"mord mathnormal\">p</span><span class=\"mopen\">[</span><span class=\"mord mathnormal\" style=\"margin-right:0.05764em;\">S</span><span class=\"mclose\">]</span><span class=\"mopen\">[</span><span class=\"mord mathnormal\" style=\"margin-right:0.03588em;\">v</span><span class=\"mclose\">]</span><span class=\"mspace\" style=\"margin-right:0.2222em;\"></span><span class=\"mbin\">+</span><span class=\"mspace\" style=\"margin-right:0.2222em;\"></span></span><span class=\"base\"><span class=\"strut\" style=\"height:1em;vertical-align:-0.25em;\"></span><span class=\"mord text\"><span class=\"mord\">cost</span></span><span class=\"mopen\">[</span><span class=\"mord mathnormal\" style=\"margin-right:0.03588em;\">v</span><span class=\"mclose\">]</span><span class=\"mopen\">[</span><span class=\"mord mathnormal\">u</span><span class=\"mclose\">])</span></span></span></span></span>","enumerator":"1","key":"xg882YYiXC"},{"type":"paragraph","position":{"start":{"line":11,"column":1},"end":{"line":11,"column":1}},"children":[{"type":"text","value":"計算量: O(2^n × n^2)","position":{"start":{"line":11,"column":1},"end":{"line":11,"column":1}},"key":"k5g6BGtvyC"}],"key":"giQZH7QOQq"}],"key":"WAKCfrML4U"},{"type":"block","kind":"notebook-code","children":[{"type":"code","lang":"python","executable":true,"value":"import math\n\ndef tsp(cost: list[list[int]]) -> int:\n    \"\"\"TSP: 全頂点を1度ずつ巡回して0に戻る最小コスト\"\"\"\n    n = len(cost)\n    INF = math.inf\n    # dp[mask][v]: mask の頂点を訪問済みで現在 v にいる最小コスト\n    dp = [[INF] * n for _ in range(1 << n)]\n    dp[1][0] = 0  # 頂点0からスタート（bit 0 が立った状態）\n\n    for S in range(1 << n):\n        for v in range(n):\n            if dp[S][v] == INF:\n                continue\n            if not (S >> v) & 1:\n                continue\n            for u in range(n):\n                if (S >> u) & 1:\n                    continue  # 既訪問\n                nS = S | (1 << u)\n                dp[nS][u] = min(dp[nS][u], dp[S][v] + cost[v][u])\n\n    full = (1 << n) - 1\n    return min(dp[full][v] + cost[v][0] for v in range(1, n))\n\n# 4頂点の例\ncost = [\n    [0, 2, 9, 10],\n    [1, 0, 6,  4],\n    [15, 7, 0, 8],\n    [6, 3, 12, 0],\n]\nprint(f\"TSP最小コスト: {tsp(cost)}\")  # 期待値: 21","key":"sdKl26EZQG"},{"type":"outputs","id":"_qa0Ua3_eiQ7gFCfoV9ls","children":[{"type":"output","jupyter_data":{"name":"stdout","output_type":"stream","text":"TSP最小コスト: 21\n"},"children":[],"key":"RZ1MS69ZWc"}],"key":"aFkas4clSe"}],"key":"KFFFDeCECS"}],"key":"aODRjqrOy2"},"references":{"cite":{"order":[],"data":{}}},"footer":{"navigation":{"prev":{"title":"数学的なアルゴリズム","url":"/software-engineering/algorithms/mathematic-algorithms","group":"ソフトウェア工学"},"next":{"title":"プログラミング","url":"/software-engineering/programming","group":"ソフトウェア工学"}}},"domain":"http://localhost:3000"}