{"version":3,"kind":"Notebook","sha256":"308b50c4b43403d791552179203abe9639b779b4e769653f060a6c0892a9fc80","slug":"soft-skills.logic.index","location":"/soft_skills/logic/index.ipynb","dependencies":[],"frontmatter":{"title":"論理学","content_includes_title":false,"kernelspec":{"name":"python3","display_name":"Python 3 (ipykernel)","language":"python"},"authors":[{"nameParsed":{"literal":"mitama","family":"mitama"},"name":"mitama","id":"contributors-myst-generated-uid-0"}],"github":"https://github.com/nigimitama/notes","copyright":"© mitama","numbering":{"title":{"offset":1}},"source_url":"https://github.com/nigimitama/notes/blob/main/book/soft_skills/logic/index.ipynb","edit_url":"https://github.com/nigimitama/notes/edit/main/book/soft_skills/logic/index.ipynb","exports":[{"format":"ipynb","filename":"index.ipynb","url":"/notes/build/index-105c9bf7e2d17555a366df565772581b.ipynb"}]},"widgets":{},"mdast":{"type":"root","children":[{"type":"block","kind":"notebook-content","children":[{"type":"block","depth":1,"children":[{"type":"list","children":[{"type":"listItem","children":[{"type":"link","url":"/soft-skills/logic/introduction","internal":true,"children":[{"type":"text","value":"論理学入門","key":"kZMZ6eSDvJ"}],"urlSource":"/soft-skills/logic/introduction","key":"WUQO6CKfgn"}],"key":"bX90zhDHuq"},{"type":"listItem","children":[{"type":"link","url":"/soft-skills/logic/fallacy","internal":true,"children":[{"type":"text","value":"誤謬論","key":"p1HUnAzgfQ"}],"urlSource":"/soft-skills/logic/fallacy","key":"gt9ejMypDw"}],"key":"Q2W0y1Gbgv"}],"key":"dNe3a8tR5C"}],"data":{"part":"toc:children"},"key":"vzrP8Way5W"}],"key":"nUmnLXECN2"}],"key":"iJyOKOk2BC"},"references":{"cite":{"order":[],"data":{}}},"footer":{"navigation":{"prev":{"title":"ゼロベース思考","url":"/soft-skills/thinking/zero-base-thinking","group":"ソフトスキル"},"next":{"title":"論理学入門","url":"/soft-skills/logic/introduction","group":"ソフトスキル"}}},"domain":"http://localhost:3000"}